{"name":"surf_tempest","lightmapUrl":"https://raw.githubusercontent.com/RSCSurf/SurfMaps8/main/maps/surf_tempest/lightmap.json?v=204e-63b3","leafPages":[{"first":0,"count":8192,"url":"https://raw.githubusercontent.com/RSCSurf/SurfMaps8/main/maps/surf_tempest/geom/leafpage0.json?v=204e-63b3"},{"first":8192,"count":5378,"url":"https://raw.githubusercontent.com/RSCSurf/SurfMaps8/main/maps/surf_tempest/geom/leafpage1.json?v=204e-63b3"}],"dispPages":[{"first":0,"count":0,"url":"https://raw.githubusercontent.com/RSCSurf/SurfMaps8/main/maps/surf_tempest/geom/disppage0.json?v=204e-63b3"}],"materialPages":[{"first":0,"count":68,"url":"https://raw.githubusercontent.com/RSCSurf/SurfMaps8/main/maps/surf_tempest/materials/matpage0.json?v=204e-63b3"}],"brushModelPages":[{"first":0,"count":1,"url":"https://raw.githubusercontent.com/RSCSurf/SurfMaps8/main/maps/surf_tempest/geom/bsppage0.json?v=204e-63b3"},{"first":1,"count":88,"url":"https://raw.githubusercontent.com/RSCSurf/SurfMaps8/main/maps/surf_tempest/geom/bsppage1.json?v=204e-63b3"}],"studioModelPages":[{"first":0,"count":25,"url":"https://raw.githubusercontent.com/RSCSurf/SurfMaps8/main/maps/surf_tempest/geom/mdlpage0.json?v=204e-63b3"}],"vertLightingPages":[{"first":0,"count":44,"url":"https://raw.githubusercontent.com/RSCSurf/SurfMaps8/main/maps/surf_tempest/geom/vhvpage0.json?v=204e-63b3"}],"visPages":[{"first":0,"count":4292,"url":"https://raw.githubusercontent.com/RSCSurf/SurfMaps8/main/maps/surf_tempest/geom/vispage0.json?v=204e-63b3"}],"ambientPages":[{"first":0,"count":4096,"url":"https://raw.githubusercontent.com/RSCSurf/SurfMaps8/main/maps/surf_tempest/geom/ambientpage0.json?v=204e-63b3"},{"first":4096,"count":4096,"url":"https://raw.githubusercontent.com/RSCSurf/SurfMaps8/main/maps/surf_tempest/geom/ambientpage1.json?v=204e-63b3"},{"first":8192,"count":4096,"url":"https://raw.githubusercontent.com/RSCSurf/SurfMaps8/main/maps/surf_tempest/geom/ambientpage2.json?v=204e-63b3"},{"first":12288,"count":1282,"url":"https://raw.githubusercontent.com/RSCSurf/SurfMaps8/main/maps/surf_tempest/geom/ambientpage3.json?v=204e-63b3"}],"entities":[{"skyMaterial":{"shader":"SourceUtils.Shaders.Sky","properties":[{"name":"cullFace","type":1,"value":false},{"name":"facePosX","type":4,"value":"https://raw.githubusercontent.com/RSCSurf/SurfMaps8/main/maps/surf_tempest/materials/skybox/tempestrt.vtf.json?v=204e-63b3"},{"name":"faceNegX","type":4,"value":"https://raw.githubusercontent.com/RSCSurf/SurfMaps8/main/maps/surf_tempest/materials/skybox/tempestlf.vtf.json?v=204e-63b3"},{"name":"facePosY","type":4,"value":"https://raw.githubusercontent.com/RSCSurf/SurfMaps8/main/maps/surf_tempest/materials/skybox/tempestbk.vtf.json?v=204e-63b3"},{"name":"faceNegY","type":4,"value":"https://raw.githubusercontent.com/RSCSurf/SurfMaps8/main/maps/surf_tempest/materials/skybox/tempestft.vtf.json?v=204e-63b3"},{"name":"facePosZ","type":4,"value":"https://raw.githubusercontent.com/RSCSurf/SurfMaps8/main/maps/surf_tempest/materials/skybox/tempestup.vtf.json?v=204e-63b3"},{"name":"faceNegZ","type":4,"value":"https://raw.githubusercontent.com/RSCSurf/SurfMaps8/main/maps/surf_tempest/materials/skybox/tempestdn.vtf.json?v=204e-63b3"}]},"model":0,"classname":"worldspawn"},{"classname":"light","origin":{"x":6720.0,"y":-1536.0,"z":3584.0}},{"classname":"light","origin":{"x":6080.0,"y":-1536.0,"z":3584.0}},{"classname":"light","origin":{"x":6720.0,"y":-1024.0,"z":3328.0}},{"classname":"light","origin":{"x":6080.0,"y":-1024.0,"z":3328.0}},{"classname":"light","origin":{"x":6720.0,"y":-512.0,"z":2944.0}},{"classname":"light","origin":{"x":6080.0,"y":-512.0,"z":2944.0}},{"classname":"light","origin":{"x":6720.0,"y":0.0,"z":2688.0}},{"classname":"light","origin":{"x":6080.0,"y":0.0,"z":2688.0}},{"classname":"light","origin":{"x":6720.0,"y":384.0,"z":2432.0}},{"classname":"light","origin":{"x":6080.0,"y":384.0,"z":2432.0}},{"classname":"light","origin":{"x":6720.0,"y":896.0,"z":2176.0}},{"classname":"light","origin":{"x":6080.0,"y":896.0,"z":2176.0}},{"classname":"light","origin":{"x":6720.0,"y":1280.0,"z":1920.0}},{"classname":"light","origin":{"x":6080.0,"y":1280.0,"z":1920.0}},{"classname":"light","origin":{"x":512.0,"y":-8192.0,"z":7552.0}},{"classname":"light","origin":{"x":512.0,"y":-8960.0,"z":7552.0}},{"classname":"light","origin":{"x":512.0,"y":-9472.0,"z":7552.0}},{"classname":"light","origin":{"x":512.0,"y":-9984.0,"z":7616.0}},{"classname":"light","origin":{"x":512.0,"y":-10368.0,"z":7744.0}},{"classname":"light","origin":{"x":512.0,"y":-10752.0,"z":8000.0}},{"classname":"light","origin":{"x":-512.0,"y":-10752.0,"z":8000.0}},{"classname":"light","origin":{"x":-512.0,"y":-8192.0,"z":7552.0}},{"classname":"light","origin":{"x":-512.0,"y":-8960.0,"z":7552.0}},{"classname":"light","origin":{"x":-512.0,"y":-9472.0,"z":7552.0}},{"classname":"light","origin":{"x":-256.0,"y":-8192.0,"z":7872.0}},{"classname":"light","origin":{"x":-256.0,"y":-8960.0,"z":7872.0}},{"classname":"light","origin":{"x":-256.0,"y":-9472.0,"z":7872.0}},{"classname":"light","origin":{"x":-256.0,"y":-9984.0,"z":7936.0}},{"classname":"light","origin":{"x":-512.0,"y":-9984.0,"z":7616.0}},{"classname":"light","origin":{"x":-256.0,"y":-10368.0,"z":8064.0}},{"classname":"light","origin":{"x":-512.0,"y":-10368.0,"z":7744.0}},{"classname":"light","origin":{"x":-256.0,"y":-7424.0,"z":7872.0}},{"classname":"light","origin":{"x":256.0,"y":-7424.0,"z":7872.0}},{"classname":"light","origin":{"x":256.0,"y":-8192.0,"z":7872.0}},{"classname":"light","origin":{"x":256.0,"y":-8960.0,"z":7872.0}},{"classname":"light","origin":{"x":256.0,"y":-9472.0,"z":7872.0}},{"classname":"light","origin":{"x":256.0,"y":-9984.0,"z":7936.0}},{"classname":"light","origin":{"x":256.0,"y":-10368.0,"z":8064.0}},{"classname":"light","origin":{"x":-8704.0,"y":7040.0,"z":7360.0}},{"classname":"light","origin":{"x":-7680.0,"y":7040.0,"z":7360.0}},{"classname":"light","origin":{"x":-7680.0,"y":7488.0,"z":7296.0}},{"classname":"light","origin":{"x":-8704.0,"y":7488.0,"z":7296.0}},{"classname":"light","origin":{"x":-7680.0,"y":8128.0,"z":7360.0}},{"classname":"light","origin":{"x":-8704.0,"y":8128.0,"z":7360.0}},{"classname":"light","origin":{"x":-7680.0,"y":8704.0,"z":7488.0}},{"classname":"light","origin":{"x":-8704.0,"y":8704.0,"z":7488.0}},{"classname":"light","origin":{"x":-7680.0,"y":9152.0,"z":7744.0}},{"classname":"light","origin":{"x":-8704.0,"y":9152.0,"z":7744.0}},{"classname":"info_player_terrorist","origin":{"x":-640.0,"y":-13744.0,"z":10993.0},"angles":{"x":0.0,"y":90.0,"z":0.0}},{"classname":"info_player_terrorist","origin":{"x":-640.0,"y":-13808.0,"z":10993.0},"angles":{"x":0.0,"y":90.0,"z":0.0}},{"classname":"info_player_terrorist","origin":{"x":-640.0,"y":-13872.0,"z":10993.0},"angles":{"x":0.0,"y":90.0,"z":0.0}},{"classname":"info_player_terrorist","origin":{"x":-640.0,"y":-13936.0,"z":10993.0},"angles":{"x":0.0,"y":90.0,"z":0.0}},{"classname":"info_player_terrorist","origin":{"x":-576.0,"y":-13936.0,"z":10993.0},"angles":{"x":0.0,"y":90.0,"z":0.0}},{"classname":"info_player_terrorist","origin":{"x":-576.0,"y":-13808.0,"z":10993.0},"angles":{"x":0.0,"y":90.0,"z":0.0}},{"classname":"info_player_terrorist","origin":{"x":-576.0,"y":-13744.0,"z":10993.0},"angles":{"x":0.0,"y":90.0,"z":0.0}},{"classname":"info_player_terrorist","origin":{"x":-576.0,"y":-13872.0,"z":10993.0},"angles":{"x":0.0,"y":90.0,"z":0.0}},{"classname":"info_player_terrorist","origin":{"x":-512.0,"y":-13936.0,"z":10993.0},"angles":{"x":0.0,"y":90.0,"z":0.0}},{"classname":"info_player_terrorist","origin":{"x":-512.0,"y":-13808.0,"z":10993.0},"angles":{"x":0.0,"y":90.0,"z":0.0}},{"classname":"info_player_terrorist","origin":{"x":-512.0,"y":-13744.0,"z":10993.0},"angles":{"x":0.0,"y":90.0,"z":0.0}},{"classname":"info_player_terrorist","origin":{"x":-512.0,"y":-13872.0,"z":10993.0},"angles":{"x":0.0,"y":90.0,"z":0.0}},{"classname":"info_player_terrorist","origin":{"x":-448.0,"y":-13936.0,"z":10993.0},"angles":{"x":0.0,"y":90.0,"z":0.0}},{"classname":"info_player_terrorist","origin":{"x":-448.0,"y":-13808.0,"z":10993.0},"angles":{"x":0.0,"y":90.0,"z":0.0}},{"classname":"info_player_terrorist","origin":{"x":-448.0,"y":-13744.0,"z":10993.0},"angles":{"x":0.0,"y":90.0,"z":0.0}},{"classname":"info_player_terrorist","origin":{"x":-448.0,"y":-13872.0,"z":10993.0},"angles":{"x":0.0,"y":90.0,"z":0.0}},{"classname":"info_player_terrorist","origin":{"x":-384.0,"y":-13936.0,"z":10993.0},"angles":{"x":0.0,"y":90.0,"z":0.0}},{"classname":"info_player_terrorist","origin":{"x":-384.0,"y":-13808.0,"z":10993.0},"angles":{"x":0.0,"y":90.0,"z":0.0}},{"classname":"info_player_terrorist","origin":{"x":-384.0,"y":-13744.0,"z":10993.0},"angles":{"x":0.0,"y":90.0,"z":0.0}},{"classname":"info_player_terrorist","origin":{"x":-384.0,"y":-13872.0,"z":10993.0},"angles":{"x":0.0,"y":90.0,"z":0.0}},{"classname":"info_player_terrorist","origin":{"x":-320.0,"y":-13936.0,"z":10993.0},"angles":{"x":0.0,"y":90.0,"z":0.0}},{"classname":"info_player_terrorist","origin":{"x":-320.0,"y":-13808.0,"z":10993.0},"angles":{"x":0.0,"y":90.0,"z":0.0}},{"classname":"info_player_terrorist","origin":{"x":-320.0,"y":-13744.0,"z":10993.0},"angles":{"x":0.0,"y":90.0,"z":0.0}},{"classname":"info_player_terrorist","origin":{"x":-320.0,"y":-13872.0,"z":10993.0},"angles":{"x":0.0,"y":90.0,"z":0.0}},{"classname":"info_player_terrorist","origin":{"x":-256.0,"y":-13936.0,"z":10993.0},"angles":{"x":0.0,"y":90.0,"z":0.0}},{"classname":"info_player_terrorist","origin":{"x":-256.0,"y":-13808.0,"z":10993.0},"angles":{"x":0.0,"y":90.0,"z":0.0}},{"classname":"info_player_terrorist","origin":{"x":-256.0,"y":-13744.0,"z":10993.0},"angles":{"x":0.0,"y":90.0,"z":0.0}},{"classname":"info_player_terrorist","origin":{"x":-256.0,"y":-13872.0,"z":10993.0},"angles":{"x":0.0,"y":90.0,"z":0.0}},{"classname":"info_player_terrorist","origin":{"x":-192.0,"y":-13936.0,"z":10993.0},"angles":{"x":0.0,"y":90.0,"z":0.0}},{"classname":"info_player_terrorist","origin":{"x":-192.0,"y":-13808.0,"z":10993.0},"angles":{"x":0.0,"y":90.0,"z":0.0}},{"classname":"info_player_terrorist","origin":{"x":-192.0,"y":-13744.0,"z":10993.0},"angles":{"x":0.0,"y":90.0,"z":0.0}},{"classname":"info_player_terrorist","origin":{"x":-192.0,"y":-13872.0,"z":10993.0},"angles":{"x":0.0,"y":90.0,"z":0.0}},{"classname":"info_player_terrorist","origin":{"x":-128.0,"y":-13936.0,"z":10993.0},"angles":{"x":0.0,"y":90.0,"z":0.0}},{"classname":"info_player_terrorist","origin":{"x":-128.0,"y":-13808.0,"z":10993.0},"angles":{"x":0.0,"y":90.0,"z":0.0}},{"classname":"info_player_terrorist","origin":{"x":-128.0,"y":-13744.0,"z":10993.0},"angles":{"x":0.0,"y":90.0,"z":0.0}},{"classname":"info_player_terrorist","origin":{"x":-128.0,"y":-13872.0,"z":10993.0},"angles":{"x":0.0,"y":90.0,"z":0.0}},{"classname":"info_player_counterterrorist","origin":{"x":576.0,"y":-13936.0,"z":10993.0},"angles":{"x":0.0,"y":90.0,"z":0.0}},{"classname":"info_player_counterterrorist","origin":{"x":576.0,"y":-13808.0,"z":10993.0},"angles":{"x":0.0,"y":90.0,"z":0.0}},{"classname":"info_player_counterterrorist","origin":{"x":576.0,"y":-13744.0,"z":10993.0},"angles":{"x":0.0,"y":90.0,"z":0.0}},{"classname":"info_player_counterterrorist","origin":{"x":576.0,"y":-13872.0,"z":10993.0},"angles":{"x":0.0,"y":90.0,"z":0.0}},{"classname":"info_player_counterterrorist","origin":{"x":512.0,"y":-13936.0,"z":10993.0},"angles":{"x":0.0,"y":90.0,"z":0.0}},{"classname":"info_player_counterterrorist","origin":{"x":512.0,"y":-13808.0,"z":10993.0},"angles":{"x":0.0,"y":90.0,"z":0.0}},{"classname":"info_player_counterterrorist","origin":{"x":512.0,"y":-13744.0,"z":10993.0},"angles":{"x":0.0,"y":90.0,"z":0.0}},{"classname":"info_player_counterterrorist","origin":{"x":512.0,"y":-13872.0,"z":10993.0},"angles":{"x":0.0,"y":90.0,"z":0.0}},{"classname":"info_player_counterterrorist","origin":{"x":448.0,"y":-13936.0,"z":10993.0},"angles":{"x":0.0,"y":90.0,"z":0.0}},{"classname":"info_player_counterterrorist","origin":{"x":448.0,"y":-13808.0,"z":10993.0},"angles":{"x":0.0,"y":90.0,"z":0.0}},{"classname":"info_player_counterterrorist","origin":{"x":448.0,"y":-13744.0,"z":10993.0},"angles":{"x":0.0,"y":90.0,"z":0.0}},{"classname":"info_player_counterterrorist","origin":{"x":448.0,"y":-13872.0,"z":10993.0},"angles":{"x":0.0,"y":90.0,"z":0.0}},{"classname":"info_player_counterterrorist","origin":{"x":384.0,"y":-13936.0,"z":10993.0},"angles":{"x":0.0,"y":90.0,"z":0.0}},{"classname":"info_player_counterterrorist","origin":{"x":384.0,"y":-13808.0,"z":10993.0},"angles":{"x":0.0,"y":90.0,"z":0.0}},{"classname":"info_player_counterterrorist","origin":{"x":384.0,"y":-13744.0,"z":10993.0},"angles":{"x":0.0,"y":90.0,"z":0.0}},{"classname":"info_player_counterterrorist","origin":{"x":384.0,"y":-13872.0,"z":10993.0},"angles":{"x":0.0,"y":90.0,"z":0.0}},{"classname":"info_player_counterterrorist","origin":{"x":320.0,"y":-13936.0,"z":10993.0},"angles":{"x":0.0,"y":90.0,"z":0.0}},{"classname":"info_player_counterterrorist","origin":{"x":320.0,"y":-13808.0,"z":10993.0},"angles":{"x":0.0,"y":90.0,"z":0.0}},{"classname":"info_player_counterterrorist","origin":{"x":320.0,"y":-13744.0,"z":10993.0},"angles":{"x":0.0,"y":90.0,"z":0.0}},{"classname":"info_player_counterterrorist","origin":{"x":320.0,"y":-13872.0,"z":10993.0},"angles":{"x":0.0,"y":90.0,"z":0.0}},{"classname":"info_player_counterterrorist","origin":{"x":256.0,"y":-13936.0,"z":10993.0},"angles":{"x":0.0,"y":90.0,"z":0.0}},{"classname":"info_player_counterterrorist","origin":{"x":256.0,"y":-13808.0,"z":10993.0},"angles":{"x":0.0,"y":90.0,"z":0.0}},{"classname":"info_player_counterterrorist","origin":{"x":256.0,"y":-13744.0,"z":10993.0},"angles":{"x":0.0,"y":90.0,"z":0.0}},{"classname":"info_player_counterterrorist","origin":{"x":256.0,"y":-13872.0,"z":10993.0},"angles":{"x":0.0,"y":90.0,"z":0.0}},{"classname":"info_player_counterterrorist","origin":{"x":192.0,"y":-13936.0,"z":10993.0},"angles":{"x":0.0,"y":90.0,"z":0.0}},{"classname":"info_player_counterterrorist","origin":{"x":192.0,"y":-13808.0,"z":10993.0},"angles":{"x":0.0,"y":90.0,"z":0.0}},{"classname":"info_player_counterterrorist","origin":{"x":192.0,"y":-13744.0,"z":10993.0},"angles":{"x":0.0,"y":90.0,"z":0.0}},{"classname":"info_player_counterterrorist","origin":{"x":192.0,"y":-13872.0,"z":10993.0},"angles":{"x":0.0,"y":90.0,"z":0.0}},{"classname":"info_player_counterterrorist","origin":{"x":128.0,"y":-13936.0,"z":10993.0},"angles":{"x":0.0,"y":90.0,"z":0.0}},{"classname":"info_player_counterterrorist","origin":{"x":128.0,"y":-13808.0,"z":10993.0},"angles":{"x":0.0,"y":90.0,"z":0.0}},{"classname":"info_player_counterterrorist","origin":{"x":128.0,"y":-13744.0,"z":10993.0},"angles":{"x":0.0,"y":90.0,"z":0.0}},{"classname":"info_player_counterterrorist","origin":{"x":128.0,"y":-13872.0,"z":10993.0},"angles":{"x":0.0,"y":90.0,"z":0.0}},{"targetname":"s1","classname":"info_teleport_destination","origin":{"x":-6.98492E-09,"y":-11776.2,"z":10960.0},"angles":{"x":0.0,"y":90.0,"z":0.0}},{"targetname":"b3","classname":"info_teleport_destination","origin":{"x":10784.0,"y":-336.0,"z":2112.0},"angles":{"x":0.0,"y":90.0,"z":0.0}},{"targetname":"b1","classname":"info_teleport_destination","origin":{"x":6400.0,"y":4608.0,"z":7346.05},"angles":{"x":0.0,"y":270.0,"z":0.0}},{"targetname":"b2","classname":"info_teleport_destination","origin":{"x":-8192.0,"y":10032.0,"z":10250.0},"angles":{"x":0.0,"y":270.0,"z":0.0}},{"classname":"func_dustmotes"},{"classname":"func_dustmotes"},{"classname":"func_dustmotes"},{"classname":"func_dustmotes"},{"classname":"func_dustmotes"},{"classname":"func_dustmotes"},{"classname":"func_dustmotes"},{"classname":"func_dustmotes"},{"classname":"func_dustmotes"},{"classname":"func_dustmotes"},{"classname":"light_spot","origin":{"x":2528.0,"y":-6000.0,"z":8368.0},"angles":{"x":0.0,"y":270.0,"z":-90.0}},{"classname":"light_spot","origin":{"x":2912.0,"y":-5616.0,"z":8608.0},"angles":{"x":0.0,"y":270.0,"z":-90.0}},{"classname":"light_spot","origin":{"x":2528.0,"y":-5872.0,"z":8848.0},"angles":{"x":0.0,"y":270.0,"z":-90.0}},{"classname":"point_spotlight","origin":{"x":2528.0,"y":-6000.0,"z":8368.0},"angles":{"x":0.0,"y":270.0,"z":-90.0}},{"classname":"point_spotlight","origin":{"x":2912.0,"y":-5616.0,"z":8608.0},"angles":{"x":0.0,"y":270.0,"z":-90.0}},{"classname":"point_spotlight","origin":{"x":2528.0,"y":-5872.0,"z":8848.0},"angles":{"x":0.0,"y":270.0,"z":-90.0}},{"classname":"light","origin":{"x":512.0,"y":-5120.0,"z":8704.0}},{"classname":"light","origin":{"x":512.0,"y":-4096.0,"z":8704.0}},{"classname":"light","origin":{"x":512.0,"y":-3072.0,"z":8704.0}},{"classname":"light","origin":{"x":512.0,"y":-2048.0,"z":8704.0}},{"classname":"light","origin":{"x":-512.0,"y":-2048.0,"z":8704.0}},{"classname":"light","origin":{"x":-512.0,"y":-3072.0,"z":8704.0}},{"classname":"light","origin":{"x":-512.0,"y":-4096.0,"z":8704.0}},{"classname":"light","origin":{"x":-512.0,"y":-5120.0,"z":8704.0}},{"classname":"light","origin":{"x":-1792.0,"y":-4096.0,"z":7936.0}},{"classname":"light","origin":{"x":1792.0,"y":-4096.0,"z":7936.0}},{"classname":"light","origin":{"x":1792.0,"y":-3072.0,"z":7936.0}},{"classname":"light","origin":{"x":-1792.0,"y":-3072.0,"z":7936.0}},{"classname":"light","origin":{"x":1792.0,"y":-2048.0,"z":7936.0}},{"classname":"light","origin":{"x":-1792.0,"y":-2048.0,"z":7936.0}},{"classname":"light","origin":{"x":1792.0,"y":-1024.0,"z":7936.0}},{"classname":"light","origin":{"x":-1792.0,"y":-1024.0,"z":7936.0}},{"classname":"light","origin":{"x":768.0,"y":512.0,"z":9088.0}},{"classname":"light","origin":{"x":-768.0,"y":512.0,"z":9088.0}},{"classname":"light","origin":{"x":-512.0,"y":1312.0,"z":9152.0}},{"classname":"light","origin":{"x":512.0,"y":1312.0,"z":9152.0}},{"classname":"light","origin":{"x":-512.0,"y":2336.0,"z":9152.0}},{"classname":"light","origin":{"x":512.0,"y":2336.0,"z":9152.0}},{"classname":"light","origin":{"x":-512.0,"y":3360.0,"z":9152.0}},{"classname":"light","origin":{"x":512.0,"y":3360.0,"z":9152.0}},{"classname":"light","origin":{"x":-512.0,"y":4384.0,"z":9152.0}},{"classname":"light","origin":{"x":512.0,"y":4384.0,"z":9152.0}},{"classname":"light","origin":{"x":-512.0,"y":5408.0,"z":9152.0}},{"classname":"light","origin":{"x":512.0,"y":5408.0,"z":9152.0}},{"classname":"light","origin":{"x":-768.0,"y":2304.0,"z":8416.0}},{"classname":"light","origin":{"x":768.0,"y":2304.0,"z":8416.0}},{"classname":"light","origin":{"x":768.0,"y":3328.0,"z":8416.0}},{"classname":"light","origin":{"x":-768.0,"y":3328.0,"z":8416.0}},{"classname":"light","origin":{"x":768.0,"y":4352.0,"z":8416.0}},{"classname":"light","origin":{"x":-768.0,"y":4352.0,"z":8416.0}},{"classname":"light","origin":{"x":768.0,"y":3840.0,"z":7776.0}},{"classname":"light","origin":{"x":-768.0,"y":3840.0,"z":7776.0}},{"classname":"light","origin":{"x":768.0,"y":3072.0,"z":7520.0}},{"classname":"light","origin":{"x":-768.0,"y":3072.0,"z":7520.0}},{"classname":"light","origin":{"x":768.0,"y":2048.0,"z":7520.0}},{"classname":"light","origin":{"x":-768.0,"y":2048.0,"z":7520.0}},{"classname":"light","origin":{"x":768.0,"y":1024.0,"z":7520.0}},{"classname":"light","origin":{"x":-768.0,"y":1024.0,"z":7520.0}},{"classname":"light","origin":{"x":1280.0,"y":2560.0,"z":6304.0}},{"classname":"light","origin":{"x":-1280.0,"y":2560.0,"z":6304.0}},{"classname":"light","origin":{"x":1280.0,"y":1536.0,"z":6240.0}},{"classname":"light","origin":{"x":-1280.0,"y":1536.0,"z":6240.0}},{"classname":"light","origin":{"x":1280.0,"y":512.0,"z":6240.0}},{"classname":"light","origin":{"x":-1280.0,"y":512.0,"z":6240.0}},{"classname":"light","origin":{"x":1280.0,"y":-512.0,"z":6240.0}},{"classname":"light","origin":{"x":-1280.0,"y":-512.0,"z":6240.0}},{"classname":"light","origin":{"x":1280.0,"y":-1536.0,"z":6240.0}},{"classname":"light","origin":{"x":-1280.0,"y":-1536.0,"z":6240.0}},{"classname":"light","origin":{"x":0.0,"y":-1536.0,"z":6448.0}},{"classname":"light","origin":{"x":0.0,"y":-512.0,"z":6448.0}},{"classname":"light","origin":{"x":0.0,"y":512.0,"z":6448.0}},{"classname":"light","origin":{"x":0.0,"y":1536.0,"z":6448.0}},{"classname":"light","origin":{"x":0.0,"y":2560.0,"z":6448.0}},{"classname":"light","origin":{"x":0.0,"y":3392.0,"z":6448.0}},{"classname":"light","origin":{"x":0.0,"y":4416.0,"z":6448.0}},{"classname":"light","origin":{"x":0.0,"y":7168.0,"z":6640.0}},{"classname":"light","origin":{"x":0.0,"y":7680.0,"z":5744.0}},{"classname":"light","origin":{"x":0.0,"y":7680.0,"z":4720.0}},{"classname":"light","origin":{"x":-768.0,"y":8448.0,"z":3248.0}},{"classname":"light","origin":{"x":768.0,"y":8448.0,"z":3248.0}},{"classname":"light","origin":{"x":768.0,"y":6912.0,"z":3248.0}},{"classname":"light","origin":{"x":-768.0,"y":6912.0,"z":3248.0}},{"classname":"light","origin":{"x":-1792.0,"y":6016.0,"z":4720.0}},{"classname":"light","origin":{"x":-1792.0,"y":6016.0,"z":5488.0}},{"classname":"light","origin":{"x":1792.0,"y":6016.0,"z":4720.0}},{"classname":"light","origin":{"x":1792.0,"y":6016.0,"z":5488.0}},{"classname":"light","origin":{"x":0.0,"y":7680.0,"z":1648.0}},{"classname":"light","origin":{"x":-1024.0,"y":8704.0,"z":896.0}},{"classname":"light","origin":{"x":1024.0,"y":8704.0,"z":896.0}},{"classname":"light","origin":{"x":1024.0,"y":6656.0,"z":896.0}},{"classname":"light","origin":{"x":-1024.0,"y":6656.0,"z":896.0}},{"classname":"light","origin":{"x":0.0,"y":7680.0,"z":-128.0}},{"classname":"light","origin":{"x":0.0,"y":7680.0,"z":-1152.0}},{"classname":"light","origin":{"x":0.0,"y":7680.0,"z":-2176.0}},{"classname":"light","origin":{"x":-1536.0,"y":7680.0,"z":-3200.0}},{"classname":"light","origin":{"x":1536.0,"y":7680.0,"z":-3200.0}},{"classname":"light","origin":{"x":-1536.0,"y":7680.0,"z":-4224.0}},{"classname":"light","origin":{"x":1536.0,"y":7680.0,"z":-4224.0}},{"classname":"light","origin":{"x":-1280.0,"y":6656.0,"z":-2688.0}},{"classname":"light","origin":{"x":1280.0,"y":6656.0,"z":-2688.0}},{"classname":"light","origin":{"x":512.0,"y":5120.0,"z":-4224.0}},{"classname":"light","origin":{"x":-512.0,"y":5120.0,"z":-4224.0}},{"classname":"light","origin":{"x":768.0,"y":4096.0,"z":-3712.0}},{"classname":"light","origin":{"x":-768.0,"y":4096.0,"z":-3712.0}},{"classname":"light","origin":{"x":768.0,"y":3072.0,"z":-3200.0}},{"classname":"light","origin":{"x":-768.0,"y":3072.0,"z":-3200.0}},{"classname":"light","origin":{"x":512.0,"y":2048.0,"z":-3200.0}},{"classname":"light","origin":{"x":-512.0,"y":2048.0,"z":-3200.0}},{"classname":"light","origin":{"x":-512.0,"y":0.0,"z":-3072.0}},{"classname":"light","origin":{"x":512.0,"y":0.0,"z":-3072.0}},{"classname":"light","origin":{"x":896.0,"y":-3072.0,"z":-2880.0}},{"classname":"light","origin":{"x":-896.0,"y":-3072.0,"z":-2880.0}},{"classname":"light","origin":{"x":-896.0,"y":-4096.0,"z":-2816.0}},{"classname":"light","origin":{"x":896.0,"y":-4096.0,"z":-2816.0}},{"classname":"light","origin":{"x":0.0,"y":-5120.0,"z":-2816.0}},{"classname":"light","origin":{"x":1280.0,"y":-6144.0,"z":-3776.0}},{"classname":"light","origin":{"x":-1280.0,"y":-6144.0,"z":-3776.0}},{"classname":"light","origin":{"x":-512.0,"y":-3840.0,"z":-3712.0}},{"classname":"light","origin":{"x":1280.0,"y":-6144.0,"z":-4736.0}},{"classname":"light","origin":{"x":-1280.0,"y":-6144.0,"z":-4736.0}},{"classname":"light","origin":{"x":-1088.0,"y":-4096.0,"z":-5312.0}},{"classname":"light","origin":{"x":1088.0,"y":-4096.0,"z":-5312.0}},{"classname":"light","origin":{"x":0.0,"y":-5120.0,"z":-4800.0}},{"classname":"light","origin":{"x":0.0,"y":-3840.0,"z":-6336.0}},{"classname":"light","origin":{"x":-1536.0,"y":-4096.0,"z":-6080.0}},{"classname":"light","origin":{"x":1536.0,"y":-4096.0,"z":-6080.0}},{"classname":"light","origin":{"x":896.0,"y":-2048.0,"z":-2880.0}},{"classname":"light","origin":{"x":-896.0,"y":-2048.0,"z":-2880.0}},{"classname":"light","origin":{"x":896.0,"y":-1024.0,"z":-2880.0}},{"classname":"light","origin":{"x":-896.0,"y":-1024.0,"z":-2880.0}},{"classname":"light","origin":{"x":-1280.0,"y":-3232.0,"z":-6144.0}},{"classname":"light","origin":{"x":1280.0,"y":-3232.0,"z":-6144.0}},{"classname":"light","origin":{"x":1280.0,"y":-2208.0,"z":-6144.0}},{"classname":"light","origin":{"x":-1280.0,"y":-2208.0,"z":-6144.0}},{"classname":"light","origin":{"x":1280.0,"y":-1184.0,"z":-6144.0}},{"classname":"light","origin":{"x":-1280.0,"y":-1184.0,"z":-6144.0}},{"classname":"light","origin":{"x":-1536.0,"y":-4864.0,"z":-6208.0}},{"classname":"light","origin":{"x":1536.0,"y":-4864.0,"z":-6208.0}},{"classname":"light","origin":{"x":-1792.0,"y":-5888.0,"z":-6080.0}},{"classname":"light","origin":{"x":1792.0,"y":-5888.0,"z":-6080.0}},{"classname":"light","origin":{"x":-1024.0,"y":-160.0,"z":-6272.0}},{"classname":"light","origin":{"x":-1024.0,"y":864.0,"z":-6784.0}},{"classname":"light","origin":{"x":-1024.0,"y":1888.0,"z":-7296.0}},{"classname":"light","origin":{"x":-1024.0,"y":2912.0,"z":-7552.0}},{"classname":"light","origin":{"x":0.0,"y":3936.0,"z":-7552.0}},{"classname":"light","origin":{"x":-1152.0,"y":3936.0,"z":-8064.0}},{"classname":"light","origin":{"x":1152.0,"y":3936.0,"z":-8064.0}},{"classname":"light_spot","origin":{"x":-0.513916,"y":3392.0,"z":5712.0},"angles":{"x":90.0,"y":180.0,"z":0.0}},{"classname":"point_spotlight","origin":{"x":-0.513916,"y":3392.0,"z":5712.0},"angles":{"x":-90.0,"y":180.0,"z":0.0}},{"classname":"light_spot","origin":{"x":-0.513916,"y":3904.0,"z":5712.0},"angles":{"x":90.0,"y":180.0,"z":0.0}},{"classname":"point_spotlight","origin":{"x":-0.513916,"y":3904.0,"z":5712.0},"angles":{"x":-90.0,"y":180.0,"z":0.0}},{"classname":"light_spot","origin":{"x":-0.513916,"y":4416.0,"z":5712.0},"angles":{"x":90.0,"y":180.0,"z":0.0}},{"classname":"point_spotlight","origin":{"x":-0.513916,"y":4416.0,"z":5712.0},"angles":{"x":-90.0,"y":180.0,"z":0.0}},{"classname":"light_spot","origin":{"x":-0.513916,"y":4928.0,"z":5712.0},"angles":{"x":90.0,"y":180.0,"z":0.0}},{"classname":"point_spotlight","origin":{"x":-0.513916,"y":4928.0,"z":5712.0},"angles":{"x":-90.0,"y":180.0,"z":0.0}},{"classname":"trigger_teleport","origin":{"x":-16.0,"y":-13840.0,"z":11032.0}},{"targetname":"zone_mapstart","classname":"trigger_multiple","origin":{"x":0.0,"y":-11776.0,"z":11008.0}},{"classname":"trigger_multiple","origin":{"x":-16.0,"y":-13840.0,"z":11032.0}},{"targetname":"zone_mapend","classname":"trigger_multiple","origin":{"x":0.0,"y":9856.5,"z":-7552.0}},{"classname":"light_spot","origin":{"x":-928.0,"y":6752.0,"z":4325.56},"angles":{"x":90.0,"y":180.0,"z":0.0}},{"classname":"point_spotlight","origin":{"x":-928.0,"y":6752.0,"z":4325.56},"angles":{"x":-90.0,"y":180.0,"z":0.0}},{"classname":"point_spotlight","origin":{"x":928.0,"y":6752.0,"z":4325.56},"angles":{"x":-90.0,"y":180.0,"z":0.0}},{"classname":"light_spot","origin":{"x":928.0,"y":6752.0,"z":4325.56},"angles":{"x":90.0,"y":180.0,"z":0.0}},{"classname":"point_spotlight","origin":{"x":0.0,"y":6208.0,"z":2729.03},"angles":{"x":-90.0,"y":180.0,"z":0.0}},{"classname":"light_spot","origin":{"x":0.0,"y":6208.0,"z":2729.03},"angles":{"x":90.0,"y":180.0,"z":0.0}},{"classname":"point_spotlight","origin":{"x":0.0,"y":9152.0,"z":2729.03},"angles":{"x":-90.0,"y":180.0,"z":0.0}},{"classname":"light_spot","origin":{"x":0.0,"y":9152.0,"z":2729.03},"angles":{"x":90.0,"y":180.0,"z":0.0}},{"classname":"point_spotlight","origin":{"x":1472.0,"y":7680.0,"z":2729.03},"angles":{"x":-90.0,"y":180.0,"z":0.0}},{"classname":"light_spot","origin":{"x":1472.0,"y":7680.0,"z":2729.03},"angles":{"x":90.0,"y":180.0,"z":0.0}},{"classname":"point_spotlight","origin":{"x":-1472.0,"y":7680.0,"z":2729.03},"angles":{"x":-90.0,"y":180.0,"z":0.0}},{"classname":"light_spot","origin":{"x":-1472.0,"y":7680.0,"z":2729.03},"angles":{"x":90.0,"y":180.0,"z":0.0}},{"classname":"point_spotlight","origin":{"x":0.0,"y":-4416.0,"z":-6342.97},"angles":{"x":-90.0,"y":180.0,"z":0.0}},{"classname":"light_spot","origin":{"x":0.0,"y":-4416.0,"z":-6342.97},"angles":{"x":90.0,"y":180.0,"z":0.0}},{"classname":"point_spotlight","origin":{"x":0.0,"y":5376.0,"z":-3072.0},"angles":{"x":90.0,"y":0.0,"z":0.0}},{"classname":"light_spot","origin":{"x":0.0,"y":1280.0,"z":-3072.0},"angles":{"x":-90.0,"y":0.0,"z":0.0}},{"classname":"light_spot","origin":{"x":0.0,"y":2304.0,"z":-3072.0},"angles":{"x":-90.0,"y":0.0,"z":0.0}},{"classname":"light_spot","origin":{"x":0.0,"y":3328.0,"z":-3072.0},"angles":{"x":-90.0,"y":0.0,"z":0.0}},{"classname":"light_spot","origin":{"x":0.0,"y":4352.0,"z":-3072.0},"angles":{"x":-90.0,"y":0.0,"z":0.0}},{"classname":"light_spot","origin":{"x":0.0,"y":5376.0,"z":-3072.0},"angles":{"x":-90.0,"y":0.0,"z":0.0}},{"classname":"point_spotlight","origin":{"x":0.0,"y":4352.0,"z":-3072.0},"angles":{"x":90.0,"y":0.0,"z":0.0}},{"classname":"point_spotlight","origin":{"x":0.0,"y":3328.0,"z":-3072.0},"angles":{"x":90.0,"y":0.0,"z":0.0}},{"classname":"point_spotlight","origin":{"x":0.0,"y":2304.0,"z":-3072.0},"angles":{"x":90.0,"y":0.0,"z":0.0}},{"classname":"point_spotlight","origin":{"x":0.0,"y":1280.0,"z":-3072.0},"angles":{"x":90.0,"y":0.0,"z":0.0}},{"classname":"light","origin":{"x":-448.0,"y":-5632.0,"z":-3776.0}},{"classname":"light","origin":{"x":448.0,"y":-5632.0,"z":-3776.0}},{"classname":"light","origin":{"x":-1536.0,"y":-4480.0,"z":-4800.0}},{"classname":"light","origin":{"x":1536.0,"y":-4480.0,"z":-4800.0}},{"classname":"light","origin":{"x":512.0,"y":-3840.0,"z":-3712.0}},{"classname":"light","origin":{"x":-512.0,"y":-4864.0,"z":-3712.0}},{"classname":"light","origin":{"x":512.0,"y":-4864.0,"z":-3712.0}},{"classname":"light","origin":{"x":0.0,"y":4608.0,"z":-5188.23}},{"classname":"light","origin":{"x":0.0,"y":5120.0,"z":-5188.23}},{"classname":"light","origin":{"x":0.0,"y":5632.0,"z":-5124.23}},{"classname":"light","origin":{"x":0.0,"y":6144.0,"z":-4932.23}},{"classname":"light","origin":{"x":0.0,"y":6656.0,"z":-4580.23}},{"classname":"light","origin":{"x":0.0,"y":7168.0,"z":-3940.23}},{"classname":"light","origin":{"x":0.0,"y":7424.0,"z":-3328.0}},{"classname":"light","origin":{"x":-768.0,"y":2304.0,"z":5856.0}},{"classname":"light","origin":{"x":-768.0,"y":1280.0,"z":5856.0}},{"classname":"light","origin":{"x":-768.0,"y":256.0,"z":5856.0}},{"classname":"light","origin":{"x":-768.0,"y":-768.0,"z":5856.0}},{"classname":"light","origin":{"x":768.0,"y":2304.0,"z":5856.0}},{"classname":"light","origin":{"x":768.0,"y":1280.0,"z":5856.0}},{"classname":"light","origin":{"x":768.0,"y":-768.0,"z":5856.0}},{"classname":"light","origin":{"x":768.0,"y":256.0,"z":5856.0}},{"classname":"light","origin":{"x":512.0,"y":8768.0,"z":4672.0}},{"classname":"light","origin":{"x":-512.0,"y":8768.0,"z":4672.0}},{"classname":"light","origin":{"x":-512.0,"y":7296.0,"z":-3712.0}},{"classname":"light","origin":{"x":-512.0,"y":7040.0,"z":-4224.0}},{"classname":"light","origin":{"x":-512.0,"y":6528.0,"z":-4736.0}},{"classname":"light","origin":{"x":-512.0,"y":6016.0,"z":-4992.0}},{"classname":"light","origin":{"x":-512.0,"y":5504.0,"z":-5184.0}},{"classname":"light","origin":{"x":-512.0,"y":4736.0,"z":-5184.0}},{"classname":"light","origin":{"x":512.0,"y":7296.0,"z":-3712.0}},{"classname":"light","origin":{"x":512.0,"y":7040.0,"z":-4224.0}},{"classname":"light","origin":{"x":512.0,"y":6528.0,"z":-4736.0}},{"classname":"light","origin":{"x":512.0,"y":6016.0,"z":-4992.0}},{"classname":"light","origin":{"x":512.0,"y":5504.0,"z":-5184.0}},{"classname":"light","origin":{"x":512.0,"y":4736.0,"z":-5184.0}},{"classname":"light","origin":{"x":1792.0,"y":-3584.0,"z":7936.0}},{"classname":"light","origin":{"x":-1792.0,"y":-3584.0,"z":7936.0}},{"classname":"light","origin":{"x":1792.0,"y":-2560.0,"z":7936.0}},{"classname":"light","origin":{"x":-1792.0,"y":-2560.0,"z":7936.0}},{"classname":"light","origin":{"x":1792.0,"y":-1536.0,"z":7936.0}},{"classname":"light","origin":{"x":-1792.0,"y":-1536.0,"z":7936.0}},{"classname":"light","origin":{"x":0.0,"y":3904.0,"z":6448.0}},{"classname":"light","origin":{"x":0.0,"y":4928.0,"z":6448.0}},{"classname":"light","origin":{"x":1792.0,"y":8928.0,"z":4720.0}},{"classname":"light","origin":{"x":1792.0,"y":8928.0,"z":5488.0}},{"classname":"light","origin":{"x":-1792.0,"y":8928.0,"z":4720.0}},{"classname":"light","origin":{"x":-1792.0,"y":8928.0,"z":5488.0}},{"classname":"light","origin":{"x":0.0,"y":7680.0,"z":768.0}},{"classname":"light","origin":{"x":-1280.0,"y":6656.0,"z":-4736.0}},{"classname":"light","origin":{"x":1280.0,"y":6656.0,"z":-4736.0}},{"classname":"light","origin":{"x":-1280.0,"y":8704.0,"z":-4736.0}},{"classname":"light","origin":{"x":1280.0,"y":8704.0,"z":-4736.0}},{"classname":"light","origin":{"x":1280.0,"y":8704.0,"z":-2688.0}},{"classname":"light","origin":{"x":-1280.0,"y":8704.0,"z":-2688.0}},{"classname":"light","origin":{"x":0.0,"y":-3584.0,"z":-2816.0}},{"classname":"light","origin":{"x":1024.0,"y":1888.0,"z":-7296.0}},{"classname":"light","origin":{"x":1024.0,"y":2912.0,"z":-7552.0}},{"classname":"light","origin":{"x":1024.0,"y":-160.0,"z":-6272.0}},{"classname":"light","origin":{"x":1024.0,"y":864.0,"z":-6784.0}},{"classname":"trigger_teleport","origin":{"x":0.0,"y":-1504.0,"z":4768.0}},{"classname":"trigger_teleport","origin":{"x":0.0,"y":192.0,"z":-7168.0}},{"classname":"point_spotlight","origin":{"x":2352.0,"y":-5872.0,"z":8848.0},"angles":{"x":0.0,"y":270.0,"z":-90.0}},{"classname":"light_spot","origin":{"x":2352.0,"y":-5872.0,"z":8848.0},"angles":{"x":0.0,"y":270.0,"z":-90.0}},{"classname":"point_spotlight","origin":{"x":2704.0,"y":-5872.0,"z":8848.0},"angles":{"x":0.0,"y":270.0,"z":-90.0}},{"classname":"light_spot","origin":{"x":2704.0,"y":-5872.0,"z":8848.0},"angles":{"x":0.0,"y":270.0,"z":-90.0}},{"classname":"point_spotlight","origin":{"x":2592.0,"y":-5872.0,"z":8976.0},"angles":{"x":0.0,"y":270.0,"z":-90.0}},{"classname":"light_spot","origin":{"x":2592.0,"y":-5872.0,"z":8976.0},"angles":{"x":0.0,"y":270.0,"z":-90.0}},{"classname":"point_spotlight","origin":{"x":2464.0,"y":-5872.0,"z":8976.0},"angles":{"x":0.0,"y":270.0,"z":-90.0}},{"classname":"light_spot","origin":{"x":2464.0,"y":-5872.0,"z":8976.0},"angles":{"x":0.0,"y":270.0,"z":-90.0}},{"classname":"point_spotlight","origin":{"x":2464.0,"y":-5872.0,"z":8720.0},"angles":{"x":0.0,"y":270.0,"z":-90.0}},{"classname":"light_spot","origin":{"x":2464.0,"y":-5872.0,"z":8720.0},"angles":{"x":0.0,"y":270.0,"z":-90.0}},{"classname":"point_spotlight","origin":{"x":2592.0,"y":-5872.0,"z":8720.0},"angles":{"x":0.0,"y":270.0,"z":-90.0}},{"classname":"light_spot","origin":{"x":2592.0,"y":-5872.0,"z":8720.0},"angles":{"x":0.0,"y":270.0,"z":-90.0}},{"classname":"point_spotlight","origin":{"x":2848.0,"y":-5616.0,"z":8736.0},"angles":{"x":0.0,"y":270.0,"z":-90.0}},{"classname":"light_spot","origin":{"x":2848.0,"y":-5616.0,"z":8736.0},"angles":{"x":0.0,"y":270.0,"z":-90.0}},{"classname":"point_spotlight","origin":{"x":2976.0,"y":-5616.0,"z":8736.0},"angles":{"x":0.0,"y":270.0,"z":-90.0}},{"classname":"light_spot","origin":{"x":2976.0,"y":-5616.0,"z":8736.0},"angles":{"x":0.0,"y":270.0,"z":-90.0}},{"classname":"point_spotlight","origin":{"x":3088.0,"y":-5616.0,"z":8608.0},"angles":{"x":0.0,"y":270.0,"z":-90.0}},{"classname":"light_spot","origin":{"x":3088.0,"y":-5616.0,"z":8608.0},"angles":{"x":0.0,"y":270.0,"z":-90.0}},{"classname":"point_spotlight","origin":{"x":2976.0,"y":-5616.0,"z":8480.0},"angles":{"x":0.0,"y":270.0,"z":-90.0}},{"classname":"light_spot","origin":{"x":2976.0,"y":-5616.0,"z":8480.0},"angles":{"x":0.0,"y":270.0,"z":-90.0}},{"classname":"point_spotlight","origin":{"x":2848.0,"y":-5616.0,"z":8480.0},"angles":{"x":0.0,"y":270.0,"z":-90.0}},{"classname":"light_spot","origin":{"x":2848.0,"y":-5616.0,"z":8480.0},"angles":{"x":0.0,"y":270.0,"z":-90.0}},{"classname":"point_spotlight","origin":{"x":2736.0,"y":-5616.0,"z":8608.0},"angles":{"x":0.0,"y":270.0,"z":-90.0}},{"classname":"light_spot","origin":{"x":2736.0,"y":-5616.0,"z":8608.0},"angles":{"x":0.0,"y":270.0,"z":-90.0}},{"classname":"point_spotlight","origin":{"x":2464.0,"y":-6000.0,"z":8240.0},"angles":{"x":0.0,"y":270.0,"z":-90.0}},{"classname":"light_spot","origin":{"x":2464.0,"y":-6000.0,"z":8240.0},"angles":{"x":0.0,"y":270.0,"z":-90.0}},{"classname":"point_spotlight","origin":{"x":2352.0,"y":-6000.0,"z":8368.0},"angles":{"x":0.0,"y":270.0,"z":-90.0}},{"classname":"light_spot","origin":{"x":2352.0,"y":-6000.0,"z":8368.0},"angles":{"x":0.0,"y":270.0,"z":-90.0}},{"classname":"point_spotlight","origin":{"x":2464.0,"y":-6000.0,"z":8496.0},"angles":{"x":0.0,"y":270.0,"z":-90.0}},{"classname":"light_spot","origin":{"x":2464.0,"y":-6000.0,"z":8496.0},"angles":{"x":0.0,"y":270.0,"z":-90.0}},{"classname":"point_spotlight","origin":{"x":2592.0,"y":-6000.0,"z":8496.0},"angles":{"x":0.0,"y":270.0,"z":-90.0}},{"classname":"light_spot","origin":{"x":2592.0,"y":-6000.0,"z":8496.0},"angles":{"x":0.0,"y":270.0,"z":-90.0}},{"classname":"point_spotlight","origin":{"x":2704.0,"y":-6000.0,"z":8368.0},"angles":{"x":0.0,"y":270.0,"z":-90.0}},{"classname":"light_spot","origin":{"x":2704.0,"y":-6000.0,"z":8368.0},"angles":{"x":0.0,"y":270.0,"z":-90.0}},{"classname":"point_spotlight","origin":{"x":2592.0,"y":-6000.0,"z":8240.0},"angles":{"x":0.0,"y":270.0,"z":-90.0}},{"classname":"light_spot","origin":{"x":2592.0,"y":-6000.0,"z":8240.0},"angles":{"x":0.0,"y":270.0,"z":-90.0}},{"classname":"light_spot","origin":{"x":-2528.12,"y":-6000.0,"z":8368.0},"angles":{"x":0.0,"y":90.0,"z":-90.0}},{"classname":"light_spot","origin":{"x":-2912.12,"y":-5616.0,"z":8608.0},"angles":{"x":0.0,"y":90.0,"z":-90.0}},{"classname":"light_spot","origin":{"x":-2528.12,"y":-5872.0,"z":8848.0},"angles":{"x":0.0,"y":90.0,"z":-90.0}},{"classname":"point_spotlight","origin":{"x":-2528.12,"y":-6000.0,"z":8368.0},"angles":{"x":0.0,"y":270.0,"z":-90.0}},{"classname":"point_spotlight","origin":{"x":-2912.12,"y":-5616.0,"z":8608.0},"angles":{"x":0.0,"y":270.0,"z":-90.0}},{"classname":"point_spotlight","origin":{"x":-2528.12,"y":-5872.0,"z":8848.0},"angles":{"x":0.0,"y":270.0,"z":-90.0}},{"classname":"point_spotlight","origin":{"x":-2352.12,"y":-5872.0,"z":8848.0},"angles":{"x":0.0,"y":270.0,"z":-90.0}},{"classname":"light_spot","origin":{"x":-2352.12,"y":-5872.0,"z":8848.0},"angles":{"x":0.0,"y":90.0,"z":-90.0}},{"classname":"point_spotlight","origin":{"x":-2704.12,"y":-5872.0,"z":8848.0},"angles":{"x":0.0,"y":270.0,"z":-90.0}},{"classname":"light_spot","origin":{"x":-2704.12,"y":-5872.0,"z":8848.0},"angles":{"x":0.0,"y":90.0,"z":-90.0}},{"classname":"point_spotlight","origin":{"x":-2592.12,"y":-5872.0,"z":8976.0},"angles":{"x":0.0,"y":270.0,"z":-90.0}},{"classname":"light_spot","origin":{"x":-2592.12,"y":-5872.0,"z":8976.0},"angles":{"x":0.0,"y":90.0,"z":-90.0}},{"classname":"point_spotlight","origin":{"x":-2464.12,"y":-5872.0,"z":8976.0},"angles":{"x":0.0,"y":270.0,"z":-90.0}},{"classname":"light_spot","origin":{"x":-2464.12,"y":-5872.0,"z":8976.0},"angles":{"x":0.0,"y":90.0,"z":-90.0}},{"classname":"point_spotlight","origin":{"x":-2464.12,"y":-5872.0,"z":8720.0},"angles":{"x":0.0,"y":270.0,"z":-90.0}},{"classname":"light_spot","origin":{"x":-2464.12,"y":-5872.0,"z":8720.0},"angles":{"x":0.0,"y":90.0,"z":-90.0}},{"classname":"point_spotlight","origin":{"x":-2592.12,"y":-5872.0,"z":8720.0},"angles":{"x":0.0,"y":270.0,"z":-90.0}},{"classname":"light_spot","origin":{"x":-2592.12,"y":-5872.0,"z":8720.0},"angles":{"x":0.0,"y":90.0,"z":-90.0}},{"classname":"point_spotlight","origin":{"x":-2848.12,"y":-5616.0,"z":8736.0},"angles":{"x":0.0,"y":270.0,"z":-90.0}},{"classname":"light_spot","origin":{"x":-2848.12,"y":-5616.0,"z":8736.0},"angles":{"x":0.0,"y":90.0,"z":-90.0}},{"classname":"point_spotlight","origin":{"x":-2976.12,"y":-5616.0,"z":8736.0},"angles":{"x":0.0,"y":270.0,"z":-90.0}},{"classname":"light_spot","origin":{"x":-2976.12,"y":-5616.0,"z":8736.0},"angles":{"x":0.0,"y":90.0,"z":-90.0}},{"classname":"point_spotlight","origin":{"x":-3088.12,"y":-5616.0,"z":8608.0},"angles":{"x":0.0,"y":270.0,"z":-90.0}},{"classname":"light_spot","origin":{"x":-3088.12,"y":-5616.0,"z":8608.0},"angles":{"x":0.0,"y":90.0,"z":-90.0}},{"classname":"point_spotlight","origin":{"x":-2976.12,"y":-5616.0,"z":8480.0},"angles":{"x":0.0,"y":270.0,"z":-90.0}},{"classname":"light_spot","origin":{"x":-2976.12,"y":-5616.0,"z":8480.0},"angles":{"x":0.0,"y":90.0,"z":-90.0}},{"classname":"point_spotlight","origin":{"x":-2848.12,"y":-5616.0,"z":8480.0},"angles":{"x":0.0,"y":270.0,"z":-90.0}},{"classname":"light_spot","origin":{"x":-2848.12,"y":-5616.0,"z":8480.0},"angles":{"x":0.0,"y":90.0,"z":-90.0}},{"classname":"point_spotlight","origin":{"x":-2736.12,"y":-5616.0,"z":8608.0},"angles":{"x":0.0,"y":270.0,"z":-90.0}},{"classname":"light_spot","origin":{"x":-2736.12,"y":-5616.0,"z":8608.0},"angles":{"x":0.0,"y":90.0,"z":-90.0}},{"classname":"point_spotlight","origin":{"x":-2464.12,"y":-6000.0,"z":8240.0},"angles":{"x":0.0,"y":270.0,"z":-90.0}},{"classname":"light_spot","origin":{"x":-2464.12,"y":-6000.0,"z":8240.0},"angles":{"x":0.0,"y":90.0,"z":-90.0}},{"classname":"point_spotlight","origin":{"x":-2352.12,"y":-6000.0,"z":8368.0},"angles":{"x":0.0,"y":270.0,"z":-90.0}},{"classname":"light_spot","origin":{"x":-2352.12,"y":-6000.0,"z":8368.0},"angles":{"x":0.0,"y":90.0,"z":-90.0}},{"classname":"point_spotlight","origin":{"x":-2464.12,"y":-6000.0,"z":8496.0},"angles":{"x":0.0,"y":270.0,"z":-90.0}},{"classname":"light_spot","origin":{"x":-2464.12,"y":-6000.0,"z":8496.0},"angles":{"x":0.0,"y":90.0,"z":-90.0}},{"classname":"point_spotlight","origin":{"x":-2592.12,"y":-6000.0,"z":8496.0},"angles":{"x":0.0,"y":270.0,"z":-90.0}},{"classname":"light_spot","origin":{"x":-2592.12,"y":-6000.0,"z":8496.0},"angles":{"x":0.0,"y":90.0,"z":-90.0}},{"classname":"point_spotlight","origin":{"x":-2704.12,"y":-6000.0,"z":8368.0},"angles":{"x":0.0,"y":270.0,"z":-90.0}},{"classname":"light_spot","origin":{"x":-2704.12,"y":-6000.0,"z":8368.0},"angles":{"x":0.0,"y":90.0,"z":-90.0}},{"classname":"point_spotlight","origin":{"x":-2592.12,"y":-6000.0,"z":8240.0},"angles":{"x":0.0,"y":270.0,"z":-90.0}},{"classname":"light_spot","origin":{"x":-2592.12,"y":-6000.0,"z":8240.0},"angles":{"x":0.0,"y":90.0,"z":-90.0}},{"classname":"func_dustmotes"},{"classname":"func_dustmotes"},{"classname":"light","origin":{"x":1792.0,"y":-1280.0,"z":7936.0}},{"classname":"light","origin":{"x":-1792.0,"y":-1280.0,"z":7936.0}},{"classname":"light","origin":{"x":1792.0,"y":-1792.0,"z":7936.0}},{"classname":"light","origin":{"x":-1792.0,"y":-1792.0,"z":7936.0}},{"classname":"light","origin":{"x":1792.0,"y":-2304.0,"z":7936.0}},{"classname":"light","origin":{"x":-1792.0,"y":-2304.0,"z":7936.0}},{"classname":"light","origin":{"x":1792.0,"y":-2816.0,"z":7936.0}},{"classname":"light","origin":{"x":-1792.0,"y":-2816.0,"z":7936.0}},{"classname":"light","origin":{"x":1792.0,"y":-3328.0,"z":7936.0}},{"classname":"light","origin":{"x":-1792.0,"y":-3328.0,"z":7936.0}},{"classname":"light","origin":{"x":1792.0,"y":-3840.0,"z":7936.0}},{"classname":"light","origin":{"x":-1792.0,"y":-3840.0,"z":7936.0}},{"classname":"light","origin":{"x":1792.0,"y":-4352.0,"z":7936.0}},{"classname":"light","origin":{"x":-1792.0,"y":-4352.0,"z":7936.0}},{"classname":"light","origin":{"x":1792.0,"y":-4864.0,"z":7936.0}},{"classname":"light","origin":{"x":-1792.0,"y":-4864.0,"z":7936.0}},{"classname":"env_steam","origin":{"x":2656.0,"y":-6192.0,"z":8608.0},"angles":{"x":0.0,"y":270.0,"z":90.0}},{"targetname":"endfilter","classname":"filter_activator_name","origin":{"x":0.0,"y":-1792.0,"z":6208.0}},{"classname":"trigger_teleport","origin":{"x":0.0,"y":5280.0,"z":6416.0}},{"classname":"trigger_multiple","origin":{"x":0.0,"y":-2304.0,"z":6144.0}},{"classname":"func_rotating","origin":{"x":0.0,"y":-2304.0,"z":6144.0},"angles":{"x":0.0,"y":0.0,"z":0.0}},{"classname":"func_rotating","origin":{"x":0.0,"y":-2304.0,"z":6144.0},"angles":{"x":0.0,"y":0.0,"z":0.0}},{"classname":"func_rotating","origin":{"x":0.0,"y":-2304.0,"z":6144.0},"angles":{"x":0.0,"y":0.0,"z":0.0}},{"classname":"light","origin":{"x":512.0,"y":512.0,"z":-3584.0}},{"classname":"light","origin":{"x":-512.0,"y":512.0,"z":-3584.0}},{"classname":"light","origin":{"x":512.0,"y":1280.0,"z":-3840.0}},{"classname":"light","origin":{"x":-512.0,"y":1280.0,"z":-3840.0}},{"classname":"light","origin":{"x":512.0,"y":2560.0,"z":-4096.0}},{"classname":"light","origin":{"x":-512.0,"y":2560.0,"z":-4096.0}},{"model":24,"clusters":[256,1496],"classname":"func_brush","origin":{"x":0.0,"y":9856.5,"z":-7584.0}},{"classname":"trigger_multiple","origin":{"x":10784.0,"y":5056.0,"z":2432.0}},{"targetname":"zoom","classname":"player_speedmod","origin":{"x":10784.0,"y":-224.0,"z":2136.0}},{"classname":"trigger_multiple","origin":{"x":10784.0,"y":-336.0,"z":2152.0}},{"targetname":"zone_b3start","classname":"trigger_multiple","origin":{"x":10784.0,"y":-320.0,"z":2176.0}},{"targetname":"zone_b3end","classname":"trigger_multiple","origin":{"x":10784.0,"y":10432.5,"z":2592.0}},{"targetname":"zone_b1start","classname":"trigger_multiple","origin":{"x":6400.0,"y":4608.0,"z":7264.0}},{"classname":"func_rotating","origin":{"x":6400.0,"y":2064.0,"z":6346.67},"angles":{"x":0.0,"y":0.0,"z":0.0}},{"classname":"func_rotating","origin":{"x":6400.0,"y":2064.0,"z":6346.67},"angles":{"x":0.0,"y":0.0,"z":0.0}},{"classname":"func_rotating","origin":{"x":6400.0,"y":2064.0,"z":6346.67},"angles":{"x":0.0,"y":0.0,"z":0.0}},{"classname":"func_rotating","origin":{"x":4784.0,"y":-1429.33,"z":5482.67},"angles":{"x":0.0,"y":0.0,"z":0.0}},{"classname":"func_rotating","origin":{"x":4784.0,"y":-1429.33,"z":5482.67},"angles":{"x":0.0,"y":0.0,"z":0.0}},{"classname":"func_rotating","origin":{"x":4784.0,"y":-1429.33,"z":5482.67},"angles":{"x":0.0,"y":0.0,"z":0.0}},{"classname":"func_rotating","origin":{"x":8016.0,"y":-1429.33,"z":5482.67},"angles":{"x":0.0,"y":0.0,"z":0.0}},{"classname":"func_rotating","origin":{"x":8016.0,"y":-1429.33,"z":5482.67},"angles":{"x":0.0,"y":0.0,"z":0.0}},{"classname":"func_rotating","origin":{"x":8016.0,"y":-1429.33,"z":5482.67},"angles":{"x":0.0,"y":0.0,"z":0.0}},{"classname":"func_rotating","origin":{"x":6400.0,"y":-2976.0,"z":4976.01},"angles":{"x":0.0,"y":0.0,"z":0.0}},{"classname":"func_rotating","origin":{"x":6400.0,"y":-2976.0,"z":4975.99},"angles":{"x":0.0,"y":0.0,"z":0.0}},{"classname":"func_rotating","origin":{"x":6400.0,"y":-2976.0,"z":4976.05},"angles":{"x":0.0,"y":0.0,"z":0.0}},{"classname":"func_rotating","origin":{"x":6400.0,"y":3680.0,"z":2914.67},"angles":{"x":0.0,"y":0.0,"z":0.0}},{"classname":"func_rotating","origin":{"x":6400.0,"y":3680.0,"z":2914.67},"angles":{"x":0.0,"y":0.0,"z":0.0}},{"classname":"func_rotating","origin":{"x":6400.0,"y":3680.0,"z":2914.67},"angles":{"x":0.0,"y":0.0,"z":0.0}},{"targetname":"zone_hardex_b_end","classname":"trigger_multiple","origin":{"x":6400.0,"y":12672.5,"z":2944.0}},{"classname":"trigger_teleport","origin":{"x":6400.0,"y":4736.0,"z":4608.0}},{"classname":"trigger_multiple","origin":{"x":6400.0,"y":4608.0,"z":7384.0}},{"classname":"func_dustmotes"},{"classname":"func_dustmotes"},{"model":50,"clusters":[3170,3171,3174,3791,3793,3795,3796,3797,3798],"classname":"func_brush","origin":{"x":0.0,"y":-5632.0,"z":-3744.0}},{"classname":"func_dustmotes"},{"classname":"func_dustmotes"},{"classname":"point_spotlight","origin":{"x":11520.0,"y":5056.0,"z":2144.0},"angles":{"x":-90.0,"y":180.0,"z":0.0}},{"classname":"light_spot","origin":{"x":11520.0,"y":5056.0,"z":2144.0},"angles":{"x":90.0,"y":0.0,"z":0.0}},{"classname":"light_spot","origin":{"x":10048.0,"y":5056.0,"z":2144.0},"angles":{"x":90.0,"y":0.0,"z":0.0}},{"classname":"point_spotlight","origin":{"x":10048.0,"y":5056.0,"z":2144.0},"angles":{"x":-90.0,"y":180.0,"z":0.0}},{"classname":"light_spot","origin":{"x":10048.0,"y":6080.0,"z":2144.0},"angles":{"x":90.0,"y":0.0,"z":0.0}},{"classname":"point_spotlight","origin":{"x":10048.0,"y":6080.0,"z":2144.0},"angles":{"x":-90.0,"y":180.0,"z":0.0}},{"classname":"point_spotlight","origin":{"x":11520.0,"y":6080.0,"z":2144.0},"angles":{"x":-90.0,"y":180.0,"z":0.0}},{"classname":"light_spot","origin":{"x":11520.0,"y":6080.0,"z":2144.0},"angles":{"x":90.0,"y":0.0,"z":0.0}},{"classname":"light_spot","origin":{"x":10048.0,"y":7104.0,"z":2272.0},"angles":{"x":90.0,"y":0.0,"z":0.0}},{"classname":"point_spotlight","origin":{"x":10048.0,"y":7104.0,"z":2272.0},"angles":{"x":-90.0,"y":180.0,"z":0.0}},{"classname":"point_spotlight","origin":{"x":11520.0,"y":7104.0,"z":2272.0},"angles":{"x":-90.0,"y":180.0,"z":0.0}},{"classname":"light_spot","origin":{"x":11520.0,"y":7104.0,"z":2272.0},"angles":{"x":90.0,"y":0.0,"z":0.0}},{"classname":"light_spot","origin":{"x":10048.0,"y":8128.0,"z":2464.0},"angles":{"x":90.0,"y":0.0,"z":0.0}},{"classname":"point_spotlight","origin":{"x":10048.0,"y":8128.0,"z":2464.0},"angles":{"x":-90.0,"y":180.0,"z":0.0}},{"classname":"point_spotlight","origin":{"x":11520.0,"y":8128.0,"z":2464.0},"angles":{"x":-90.0,"y":180.0,"z":0.0}},{"classname":"light_spot","origin":{"x":11520.0,"y":8128.0,"z":2464.0},"angles":{"x":90.0,"y":0.0,"z":0.0}},{"classname":"light_spot","origin":{"x":10048.0,"y":9152.0,"z":2464.0},"angles":{"x":90.0,"y":0.0,"z":0.0}},{"classname":"point_spotlight","origin":{"x":10048.0,"y":9152.0,"z":2464.0},"angles":{"x":-90.0,"y":180.0,"z":0.0}},{"classname":"point_spotlight","origin":{"x":11520.0,"y":9152.0,"z":2464.0},"angles":{"x":-90.0,"y":180.0,"z":0.0}},{"classname":"light_spot","origin":{"x":11520.0,"y":9152.0,"z":2464.0},"angles":{"x":90.0,"y":0.0,"z":0.0}},{"classname":"light_spot","origin":{"x":11520.0,"y":4032.0,"z":2240.0},"angles":{"x":90.0,"y":0.0,"z":0.0}},{"classname":"point_spotlight","origin":{"x":11520.0,"y":4032.0,"z":2240.0},"angles":{"x":-90.0,"y":180.0,"z":0.0}},{"classname":"light_spot","origin":{"x":10048.0,"y":4032.0,"z":2240.0},"angles":{"x":90.0,"y":0.0,"z":0.0}},{"classname":"point_spotlight","origin":{"x":10048.0,"y":4032.0,"z":2240.0},"angles":{"x":-90.0,"y":180.0,"z":0.0}},{"classname":"light_spot","origin":{"x":11520.0,"y":1984.0,"z":2144.0},"angles":{"x":90.0,"y":0.0,"z":0.0}},{"classname":"point_spotlight","origin":{"x":11520.0,"y":1984.0,"z":2144.0},"angles":{"x":-90.0,"y":180.0,"z":0.0}},{"classname":"light_spot","origin":{"x":10048.0,"y":1984.0,"z":2144.0},"angles":{"x":90.0,"y":0.0,"z":0.0}},{"classname":"point_spotlight","origin":{"x":10048.0,"y":1984.0,"z":2144.0},"angles":{"x":-90.0,"y":180.0,"z":0.0}},{"classname":"light_spot","origin":{"x":11520.0,"y":960.0,"z":2144.0},"angles":{"x":90.0,"y":0.0,"z":0.0}},{"classname":"point_spotlight","origin":{"x":11520.0,"y":960.0,"z":2144.0},"angles":{"x":-90.0,"y":180.0,"z":0.0}},{"classname":"light_spot","origin":{"x":10048.0,"y":960.0,"z":2144.0},"angles":{"x":90.0,"y":0.0,"z":0.0}},{"classname":"point_spotlight","origin":{"x":10048.0,"y":960.0,"z":2144.0},"angles":{"x":-90.0,"y":180.0,"z":0.0}},{"classname":"light_spot","origin":{"x":11520.0,"y":-48.0,"z":2112.0},"angles":{"x":90.0,"y":0.0,"z":0.0}},{"classname":"point_spotlight","origin":{"x":11520.0,"y":-48.0,"z":2112.0},"angles":{"x":-90.0,"y":180.0,"z":0.0}},{"classname":"light_spot","origin":{"x":10048.0,"y":-48.0,"z":2112.0},"angles":{"x":90.0,"y":0.0,"z":0.0}},{"classname":"point_spotlight","origin":{"x":10048.0,"y":-48.0,"z":2112.0},"angles":{"x":-90.0,"y":180.0,"z":0.0}},{"classname":"light_spot","origin":{"x":10048.0,"y":-592.0,"z":2112.0},"angles":{"x":90.0,"y":0.0,"z":0.0}},{"classname":"point_spotlight","origin":{"x":10048.0,"y":-592.0,"z":2112.0},"angles":{"x":-90.0,"y":180.0,"z":0.0}},{"classname":"light_spot","origin":{"x":11520.0,"y":-592.0,"z":2112.0},"angles":{"x":90.0,"y":0.0,"z":0.0}},{"classname":"point_spotlight","origin":{"x":11520.0,"y":-592.0,"z":2112.0},"angles":{"x":-90.0,"y":180.0,"z":0.0}},{"classname":"light_spot","origin":{"x":10048.0,"y":10704.0,"z":2432.0},"angles":{"x":90.0,"y":0.0,"z":0.0}},{"classname":"point_spotlight","origin":{"x":10048.0,"y":10704.0,"z":2432.0},"angles":{"x":-90.0,"y":180.0,"z":0.0}},{"classname":"light_spot","origin":{"x":11520.0,"y":10704.0,"z":2432.0},"angles":{"x":90.0,"y":0.0,"z":0.0}},{"classname":"point_spotlight","origin":{"x":11520.0,"y":10704.0,"z":2432.0},"angles":{"x":-90.0,"y":180.0,"z":0.0}},{"classname":"light","origin":{"x":896.0,"y":-2560.0,"z":-2880.0}},{"classname":"light","origin":{"x":-896.0,"y":-2560.0,"z":-2880.0}},{"model":53,"clusters":[2590,2591,2592,2593,2636,2637,2638,2639,2642,2643],"classname":"func_brush","origin":{"x":-8128.0,"y":2208.0,"z":6368.0}},{"model":54,"clusters":[3750,3946,3947,3957,3958,3963,3964,3985,3986,3991],"classname":"func_brush","origin":{"x":-8192.0,"y":-3520.0,"z":6048.0}},{"model":55,"clusters":[3928,4019,4035,4041,4071,4072],"classname":"func_brush","origin":{"x":-8192.0,"y":-6720.0,"z":4160.0}},{"model":56,"clusters":[3755,3761,3951,3956,3962,3968,3973,3978,3990,3996,4001,4006,4007,4008],"classname":"func_brush","origin":{"x":-8192.0,"y":-4000.0,"z":32.0}},{"classname":"trigger_multiple","origin":{"x":-8192.0,"y":10032.0,"z":10288.0}},{"model":58,"clusters":[4256,4257,4258,4263,4268,4272,4274,4278,4286,4288],"classname":"func_brush","origin":{"x":-8192.0,"y":-12224.0,"z":4096.0}},{"classname":"trigger_teleport","origin":{"x":-8192.0,"y":-1504.0,"z":4864.0}},{"targetname":"zone_b2end","classname":"trigger_multiple","origin":{"x":-8192.0,"y":10016.5,"z":896.0}},{"targetname":"zone_b2start","classname":"trigger_multiple","origin":{"x":-8192.0,"y":9984.0,"z":10240.0}},{"model":62,"clusters":[4042,4044,4045,4080],"classname":"func_brush","origin":{"x":-8192.0,"y":-7488.0,"z":5024.0}},{"model":63,"clusters":[3743,3941,3944,3945,3981,3982],"classname":"func_brush","origin":{"x":-8192.02,"y":-2464.0,"z":704.0}},{"model":64,"clusters":[2569,2572,2573,2581,2589,2590,2591,2592,2593,2596,2607,2623,2634,2635,2636,2637,2638,2639,2646,2648],"classname":"func_brush","origin":{"x":-8192.0,"y":3264.0,"z":-512.0}},{"model":65,"clusters":[1763,1787],"classname":"func_brush","origin":{"x":-8192.0,"y":10016.5,"z":895.99}},{"classname":"light","origin":{"x":-1024.0,"y":864.0,"z":-6272.0}},{"classname":"light","origin":{"x":-1024.0,"y":1888.0,"z":-6272.0}},{"classname":"light","origin":{"x":1024.0,"y":864.0,"z":-6272.0}},{"classname":"light","origin":{"x":-1024.0,"y":2912.0,"z":-6528.0}},{"classname":"light","origin":{"x":1024.0,"y":1888.0,"z":-6272.0}},{"classname":"light","origin":{"x":1024.0,"y":2912.0,"z":-6528.0}},{"classname":"light","origin":{"x":0.0,"y":3936.0,"z":-6400.0}},{"classname":"light","origin":{"x":0.0,"y":-5760.0,"z":-5184.0}},{"classname":"light","origin":{"x":0.0,"y":-5760.0,"z":-4544.0}},{"classname":"light","origin":{"x":0.0,"y":-5376.0,"z":-5312.0}},{"classname":"light","origin":{"x":1024.0,"y":-5120.0,"z":-5312.0}},{"classname":"light","origin":{"x":1024.0,"y":-5120.0,"z":-4800.0}},{"classname":"light","origin":{"x":-1024.0,"y":-5120.0,"z":-5312.0}},{"classname":"light","origin":{"x":-1024.0,"y":-5120.0,"z":-4800.0}},{"classname":"light","origin":{"x":1024.0,"y":4096.0,"z":-4736.0}},{"classname":"light","origin":{"x":-1024.0,"y":4096.0,"z":-4736.0}},{"classname":"light","origin":{"x":-1024.0,"y":5120.0,"z":-5248.0}},{"classname":"light","origin":{"x":1024.0,"y":5120.0,"z":-5248.0}},{"classname":"light","origin":{"x":-1024.0,"y":6144.0,"z":-4736.0}},{"classname":"light","origin":{"x":1024.0,"y":6144.0,"z":-4736.0}},{"classname":"light","origin":{"x":1920.0,"y":-7424.0,"z":-5632.0}},{"classname":"light","origin":{"x":-1920.0,"y":-7424.0,"z":-5632.0}},{"classname":"light","origin":{"x":0.0,"y":-9856.0,"z":-5376.0}},{"classname":"light","origin":{"x":0.0,"y":-2560.0,"z":-2752.0}},{"classname":"light","origin":{"x":0.0,"y":-2048.0,"z":-2752.0}},{"targetname":"endfilter2","classname":"filter_activator_name","origin":{"x":6653.18,"y":2361.6,"z":6408.0}},{"classname":"trigger_multiple","origin":{"x":6400.0,"y":2064.0,"z":6348.0}},{"classname":"trigger_multiple","origin":{"x":6400.0,"y":-1440.0,"z":5312.0}},{"classname":"trigger_teleport","origin":{"x":6400.0,"y":-2972.0,"z":4976.0}},{"classname":"trigger_multiple","origin":{"x":0.0,"y":1056.0,"z":9264.0}},{"classname":"light","origin":{"x":1408.0,"y":-7424.0,"z":-5632.0}},{"classname":"light","origin":{"x":-1408.0,"y":-7424.0,"z":-5632.0}},{"classname":"light","origin":{"x":-1920.0,"y":-7936.0,"z":-5632.0}},{"classname":"light","origin":{"x":-1408.0,"y":-7936.0,"z":-5632.0}},{"classname":"light","origin":{"x":-896.0,"y":-7936.0,"z":-5632.0}},{"classname":"light","origin":{"x":-896.0,"y":-8448.0,"z":-5632.0}},{"classname":"light","origin":{"x":-1408.0,"y":-8448.0,"z":-5632.0}},{"classname":"light","origin":{"x":-896.0,"y":-8960.0,"z":-5632.0}},{"classname":"light","origin":{"x":1408.0,"y":-7936.0,"z":-5632.0}},{"classname":"light","origin":{"x":1920.0,"y":-7936.0,"z":-5632.0}},{"classname":"light","origin":{"x":896.0,"y":-7936.0,"z":-5632.0}},{"classname":"light","origin":{"x":896.0,"y":-8448.0,"z":-5632.0}},{"classname":"light","origin":{"x":1408.0,"y":-8448.0,"z":-5632.0}},{"classname":"light","origin":{"x":896.0,"y":-8960.0,"z":-5632.0}},{"classname":"light","origin":{"x":-1920.0,"y":-6912.0,"z":-5632.0}},{"classname":"light","origin":{"x":1920.0,"y":-6912.0,"z":-5632.0}},{"classname":"light","origin":{"x":1280.0,"y":-5376.0,"z":-6080.0}},{"classname":"light","origin":{"x":768.0,"y":-4864.0,"z":-6080.0}},{"classname":"light","origin":{"x":-1280.0,"y":-5376.0,"z":-6080.0}},{"classname":"light","origin":{"x":-768.0,"y":-4864.0,"z":-6080.0}},{"classname":"light","origin":{"x":-256.0,"y":-4352.0,"z":-6080.0}},{"classname":"light","origin":{"x":256.0,"y":-4352.0,"z":-6080.0}},{"classname":"light","origin":{"x":-1152.0,"y":4864.0,"z":-8320.0}},{"classname":"light","origin":{"x":1152.0,"y":4864.0,"z":-8320.0}},{"classname":"light","origin":{"x":-1152.0,"y":4864.0,"z":-7808.0}},{"classname":"light","origin":{"x":1152.0,"y":4864.0,"z":-7808.0}},{"classname":"light","origin":{"x":-1152.0,"y":4864.0,"z":-7296.0}},{"classname":"light","origin":{"x":1152.0,"y":4864.0,"z":-7296.0}},{"classname":"light","origin":{"x":-640.0,"y":4864.0,"z":-6784.0}},{"classname":"light","origin":{"x":640.0,"y":4864.0,"z":-6784.0}},{"model":70,"clusters":[2574,2590,2591,2600],"classname":"func_brush","origin":{"x":-8192.02,"y":4896.0,"z":8544.0}},{"classname":"trigger_teleport","origin":{"x":0.0,"y":-3328.0,"z":-6144.0}},{"targetname":"endfilter3","classname":"filter_activator_name","origin":{"x":0.0,"y":-3456.0,"z":-6144.0}},{"classname":"trigger_multiple","origin":{"x":0.0,"y":-9856.0,"z":-5344.0}},{"classname":"env_steam","origin":{"x":-2656.0,"y":-6192.0,"z":8608.0},"angles":{"x":0.0,"y":270.0,"z":90.0}},{"classname":"light","origin":{"x":1408.0,"y":-8960.0,"z":-5632.0}},{"classname":"light","origin":{"x":1920.0,"y":-8960.0,"z":-5632.0}},{"classname":"light","origin":{"x":1920.0,"y":-8448.0,"z":-5632.0}},{"classname":"light","origin":{"x":1408.0,"y":-9472.0,"z":-5632.0}},{"classname":"light","origin":{"x":896.0,"y":-9472.0,"z":-5632.0}},{"classname":"light","origin":{"x":-896.0,"y":-9472.0,"z":-5632.0}},{"classname":"light","origin":{"x":-1408.0,"y":-9472.0,"z":-5632.0}},{"classname":"light","origin":{"x":-1408.0,"y":-8960.0,"z":-5632.0}},{"classname":"light","origin":{"x":-1920.0,"y":-8960.0,"z":-5632.0}},{"classname":"light","origin":{"x":-1920.0,"y":-8448.0,"z":-5632.0}},{"targetname":"start","classname":"info_teleport_destination","origin":{"x":-2938.03,"y":-14560.0,"z":10529.0},"angles":{"x":0.0,"y":0.0,"z":0.0}},{"classname":"trigger_teleport","origin":{"x":-2143.99,"y":-14561.0,"z":10608.1}},{"classname":"func_rotating","origin":{"x":-1092.03,"y":-14560.1,"z":10961.1},"angles":{"x":0.0,"y":0.0,"z":0.0}},{"model":75,"clusters":[4188,4189,4190,4191,4192,4193,4194,4195,4196,4197,4198,4199,4200,4201,4202,4203,4204,4205,4206,4207,4208,4209,4210,4211,4212,4213,4214,4215,4216,4217,4218,4219,4220,4221,4222,4223,4224,4225,4226,4227,4228,4229,4230],"targetname":"neat","classname":"func_brush","origin":{"x":-1617.86,"y":-14559.0,"z":10808.3}},{"Brightness":{"R":193,"G":255,"B":255,"A":10},"Ambient":{"R":225,"G":225,"B":255,"A":5},"BrightnessHdr":{"R":255,"G":255,"B":255,"A":1},"AmbientHdr":{"R":255,"G":255,"B":255,"A":1},"BrightnessScaleHdr":1.0,"AmbientScaleHdr":1.0,"Pitch":-27.0,"classname":"light_environment","origin":{"x":-2472.0,"y":-15144.0,"z":10544.0},"angles":{"x":-27.0,"y":90.0,"z":0.0}},{"classname":"game_player_equip","origin":{"x":-2448.0,"y":-15144.0,"z":10544.0}},{"classname":"trigger_teleport","origin":{"x":-2143.99,"y":-14177.0,"z":10608.1}},{"classname":"trigger_teleport","origin":{"x":-2143.99,"y":-14945.0,"z":10608.1}},{"classname":"trigger_teleport","origin":{"x":-1091.99,"y":-14562.0,"z":10955.8}},{"classname":"func_dustmotes"},{"classname":"func_dustmotes"},{"classname":"func_dustmotes"},{"classname":"func_dustmotes"},{"classname":"func_dustmotes"},{"classname":"func_dustmotes"},{"targetname":"disable_dmg","classname":"filter_damage_type","origin":{"x":-2424.0,"y":-15144.0,"z":10544.0}},{"classname":"light","origin":{"x":0.0,"y":-2304.0,"z":6144.0}},{"classname":"light","origin":{"x":-1152.0,"y":-9984.0,"z":-5632.0}},{"classname":"light","origin":{"x":1152.0,"y":-9984.0,"z":-5632.0}},{"classname":"light","origin":{"x":5632.0,"y":12672.0,"z":2944.0}},{"classname":"light","origin":{"x":6144.0,"y":12672.0,"z":2944.0}},{"classname":"light","origin":{"x":6656.0,"y":12672.0,"z":2944.0}},{"classname":"light","origin":{"x":7168.0,"y":12672.0,"z":2944.0}},{"classname":"light","origin":{"x":6400.0,"y":4608.0,"z":7360.0}},{"model":85,"clusters":[158,159,160,162,645,647,648,651],"classname":"func_brush","origin":{"x":6400.0,"y":6912.0,"z":2144.01}},{"model":86,"clusters":[629,638,640,642,1036,1039,1040,1041,1043,1046,1047,1049,1053],"classname":"func_brush","origin":{"x":6416.0,"y":736.0,"z":5728.01}},{"model":87,"clusters":[2661,2669,2674,2678,2681],"classname":"func_brush","origin":{"x":6400.0,"y":-1440.0,"z":5280.01}},{"model":88,"clusters":[665,666,679,681,1035,1037],"classname":"func_brush","origin":{"x":6400.0,"y":3644.9,"z":6429.69}},{"classname":"light","origin":{"x":5632.0,"y":3552.0,"z":6784.0}},{"classname":"light","origin":{"x":768.0,"y":-256.0,"z":8704.0}},{"classname":"light","origin":{"x":-768.0,"y":-256.0,"z":8704.0}},{"classname":"light","origin":{"x":-1280.0,"y":-2560.0,"z":6240.0}},{"classname":"light","origin":{"x":1280.0,"y":-2560.0,"z":6240.0}},{"classname":"light","origin":{"x":0.0,"y":-3072.0,"z":6192.0}},{"classname":"light","origin":{"x":0.0,"y":7680.0,"z":3264.0}},{"classname":"light","origin":{"x":0.0,"y":6144.0,"z":3264.0}},{"classname":"light","origin":{"x":0.0,"y":9216.0,"z":3264.0}},{"classname":"light","origin":{"x":-1536.0,"y":7680.0,"z":3264.0}},{"classname":"light","origin":{"x":1536.0,"y":7680.0,"z":3264.0}},{"classname":"light","origin":{"x":-896.0,"y":-1536.0,"z":-2880.0}},{"classname":"light","origin":{"x":896.0,"y":-1536.0,"z":-2880.0}},{"classname":"light","origin":{"x":0.0,"y":-4352.0,"z":-2816.0}},{"classname":"light","origin":{"x":512.0,"y":-4480.0,"z":-4800.0}},{"classname":"light","origin":{"x":-512.0,"y":-4480.0,"z":-4800.0}},{"classname":"light","origin":{"x":0.0,"y":-4096.0,"z":-5184.0}},{"classname":"light","origin":{"x":0.0,"y":-160.0,"z":-6272.0}},{"classname":"light","origin":{"x":0.0,"y":864.0,"z":-6272.0}},{"classname":"light","origin":{"x":0.0,"y":1888.0,"z":-6272.0}},{"classname":"light","origin":{"x":0.0,"y":864.0,"z":-6784.0}},{"classname":"light","origin":{"x":0.0,"y":1888.0,"z":-7296.0}},{"classname":"light","origin":{"x":0.0,"y":2912.0,"z":-7552.0}},{"classname":"light","origin":{"x":7168.0,"y":3552.0,"z":6784.0}},{"classname":"light","origin":{"x":0.0,"y":-3072.0,"z":-2752.0}},{"classname":"light","origin":{"x":768.0,"y":-6656.0,"z":-4736.0}},{"classname":"light","origin":{"x":768.0,"y":-6656.0,"z":-3776.0}},{"classname":"light","origin":{"x":-768.0,"y":-6656.0,"z":-3776.0}},{"classname":"light","origin":{"x":-768.0,"y":-6656.0,"z":-4736.0}},{"classname":"light","origin":{"x":1024.0,"y":-4352.0,"z":-6208.0}},{"classname":"light","origin":{"x":512.0,"y":-3840.0,"z":-6208.0}},{"classname":"light","origin":{"x":-1024.0,"y":-4352.0,"z":-6208.0}},{"classname":"light","origin":{"x":-512.0,"y":-3840.0,"z":-6208.0}},{"classname":"light","origin":{"x":-1536.0,"y":-4096.0,"z":-6592.0}},{"classname":"light","origin":{"x":1536.0,"y":-4096.0,"z":-6720.0}},{"classname":"light","origin":{"x":1920.0,"y":-4736.0,"z":-6720.0}},{"classname":"light","origin":{"x":896.0,"y":-3840.0,"z":-6720.0}},{"classname":"light","origin":{"x":-1920.0,"y":-4736.0,"z":-6592.0}},{"classname":"light","origin":{"x":-896.0,"y":-3840.0,"z":-6592.0}},{"classname":"light","origin":{"x":-1280.0,"y":-2720.0,"z":-6144.0}},{"classname":"light","origin":{"x":1280.0,"y":-2720.0,"z":-6144.0}},{"classname":"light","origin":{"x":-1280.0,"y":-1696.0,"z":-6144.0}},{"classname":"light","origin":{"x":1280.0,"y":-1696.0,"z":-6144.0}},{"classname":"light","origin":{"x":2176.0,"y":-5760.0,"z":-6464.0}},{"classname":"light","origin":{"x":-1920.0,"y":-5760.0,"z":-6464.0}},{"classname":"light","origin":{"x":-896.0,"y":-3584.0,"z":-2880.0}},{"classname":"light","origin":{"x":896.0,"y":-3584.0,"z":-2880.0}},{"model":0,"vertLighting":0,"flags":0,"clusters":[2682,2674,2672,2669,1051,1046,1045,1041,1039,1036,1035],"classname":"prop_static","origin":{"x":6400.0,"y":-210.373,"z":2752.01},"angles":{"x":0.0,"y":270.0,"z":0.0}},{"model":16,"flags":216,"clusters":[4130,4090,4088,4086,3900,3898,3882,3815,3811,3807,3282,3268,3266,3260,3246,3244,3224,3205,3202,3200],"classname":"prop_static","origin":{"x":0.0,"y":-8925.52,"z":7874.3},"angles":{"x":0.0,"y":270.0,"z":0.0}},{"model":1,"vertLighting":2,"flags":0,"clusters":[2359,2356,2267,2129,2126,2078,1234,1133,1130,1032,955,954],"classname":"prop_static","origin":{"x":-960.0,"y":2688.0,"z":-11008.0},"angles":{"x":0.0,"y":270.0,"z":0.0}},{"model":8,"vertLighting":3,"flags":0,"clusters":[3194,3182,3137,3132,3117,3106,3104,3086,3031,2983],"classname":"prop_static","origin":{"x":1184.0,"y":-5096.0,"z":-6760.0},"angles":{"x":0.0,"y":270.0,"z":0.0}},{"model":9,"vertLighting":4,"flags":0,"clusters":[3879,3871,3857,3855,3841,3836,3805,3716,3589,3588,3532],"classname":"prop_static","origin":{"x":-1184.0,"y":-5096.0,"z":-6760.0},"angles":{"x":0.0,"y":270.0,"z":0.0}},{"model":18,"vertLighting":5,"flags":0,"clusters":[3830,3677,3676,3674,3621,3620,3611,3465,3464,3462,3459,3458,3413,3412,3411,3403,3402,2524,2523,2522,2518,2468,2465,2461],"classname":"prop_static","origin":{"x":-1440.0,"y":-2560.0,"z":8032.0},"angles":{"x":0.0,"y":270.0,"z":0.0}},{"model":19,"vertLighting":6,"flags":0,"clusters":[3126,2992,2990,2912,2910,2909,2807,2805,2804,2802,2801,2739,2737,2736,2734,1414,1413,1412,1409,1362,1361,1356],"classname":"prop_static","origin":{"x":1440.0,"y":-2560.0,"z":8032.0},"angles":{"x":0.0,"y":270.0,"z":0.0}},{"model":20,"vertLighting":7,"flags":0,"clusters":[2529,2476,2444,2427,2384,2383,2345,2306,2305,2256,2255,2254],"classname":"prop_static","origin":{"x":-640.0,"y":1088.0,"z":5824.0},"angles":{"x":0.0,"y":270.0,"z":0.0}},{"model":2,"vertLighting":8,"flags":0,"clusters":[1554,1550,1548,1545,327,325,323,320],"classname":"prop_static","origin":{"x":-960.0,"y":8640.0,"z":4608.0},"angles":{"x":0.0,"y":270.0,"z":0.0}},{"model":21,"vertLighting":9,"flags":0,"clusters":[1443,1419,1385,1370,1313,1312,1270,1269,1221,1220,1219,1126,1125,1010],"classname":"prop_static","origin":{"x":640.0,"y":1088.0,"z":5825.0},"angles":{"x":0.0,"y":270.0,"z":0.0}},{"model":22,"vertLighting":10,"flags":0,"clusters":[2066,2063,2062,2009,2004,1885,1884,1881,1879,1876,1837,1834,1831,1630,1624,1614,1606,1600,1024,1016,1015,929,922,850,849,846,844,841,768,765,760,444,436,428,420,412],"classname":"prop_static","origin":{"x":0.0,"y":5592.31,"z":-4376.1},"angles":{"x":0.0,"y":270.0,"z":0.0}},{"model":3,"vertLighting":11,"flags":0,"clusters":[3362,3347,2820,2771],"classname":"prop_static","origin":{"x":-1.2251,"y":-2304.0,"z":6146.0},"angles":{"x":0.0,"y":90.0,"z":0.0}},{"model":23,"vertLighting":12,"flags":16,"clusters":[134,118],"classname":"prop_static","origin":{"x":6400.0,"y":12640.0,"z":2920.0},"angles":{"x":0.0,"y":180.0,"z":0.0}},{"model":10,"vertLighting":13,"flags":0,"clusters":[1049,1043],"classname":"prop_static","origin":{"x":6400.0,"y":-717.05,"z":5568.0},"angles":{"x":0.0,"y":180.0,"z":0.0}},{"model":24,"vertLighting":14,"flags":0,"clusters":[27],"classname":"prop_static","origin":{"x":10783.8,"y":10448.0,"z":2580.0},"angles":{"x":0.0,"y":270.0,"z":0.0}},{"model":4,"vertLighting":15,"flags":0,"clusters":[2616],"classname":"prop_static","origin":{"x":-9472.0,"y":3968.0,"z":8576.0},"angles":{"x":0.0,"y":180.0,"z":0.0}},{"model":4,"vertLighting":16,"flags":0,"clusters":[2582],"classname":"prop_static","origin":{"x":-6912.0,"y":3968.0,"z":8576.0},"angles":{"x":0.0,"y":0.0,"z":0.0}},{"model":4,"vertLighting":17,"flags":0,"clusters":[2641,2567],"classname":"prop_static","origin":{"x":-6272.0,"y":-832.0,"z":6656.0},"angles":{"x":-90.0,"y":0.0,"z":0.0}},{"model":4,"vertLighting":18,"flags":0,"clusters":[2655,2654],"classname":"prop_static","origin":{"x":-10112.0,"y":-832.001,"z":6656.0},"angles":{"x":-90.0,"y":180.0,"z":0.0}},{"model":4,"vertLighting":19,"flags":0,"clusters":[4008,4007],"classname":"prop_static","origin":{"x":-11392.0,"y":-4160.0,"z":6016.0},"angles":{"x":-15.0,"y":270.0,"z":0.0}},{"model":4,"vertLighting":20,"flags":0,"clusters":[3756,3749],"classname":"prop_static","origin":{"x":-4992.0,"y":-4160.0,"z":6016.0},"angles":{"x":-15.0,"y":270.0,"z":0.0}},{"model":4,"vertLighting":21,"flags":0,"clusters":[3944,3941],"classname":"prop_static","origin":{"x":-7306.41,"y":-2752.0,"z":2240.0},"angles":{"x":90.0,"y":180.0,"z":0.0}},{"model":4,"vertLighting":22,"flags":0,"clusters":[3981,3945],"classname":"prop_static","origin":{"x":-9080.0,"y":-2752.0,"z":2240.0},"angles":{"x":90.0,"y":0.0,"z":0.0}},{"model":4,"vertLighting":23,"flags":16,"clusters":[305,267,191,176],"classname":"prop_static","origin":{"x":2048.0,"y":9152.0,"z":4544.0},"angles":{"x":0.0,"y":270.0,"z":0.0}},{"model":4,"vertLighting":24,"flags":16,"clusters":[1650,1638,1534,1507],"classname":"prop_static","origin":{"x":-2048.0,"y":9152.0,"z":4544.0},"angles":{"x":0.0,"y":270.0,"z":0.0}},{"model":4,"vertLighting":25,"flags":16,"clusters":[730],"classname":"prop_static","origin":{"x":1216.0,"y":6464.0,"z":3360.0},"angles":{"x":45.0,"y":225.0,"z":0.0}},{"model":4,"vertLighting":26,"flags":16,"clusters":[1903],"classname":"prop_static","origin":{"x":-1216.0,"y":6464.0,"z":3360.0},"angles":{"x":45.0,"y":135.0,"z":0.0}},{"model":4,"vertLighting":27,"flags":16,"clusters":[1640],"classname":"prop_static","origin":{"x":-1216.0,"y":8928.0,"z":3360.0},"angles":{"x":45.0,"y":225.0,"z":0.0}},{"model":4,"vertLighting":28,"flags":16,"clusters":[311],"classname":"prop_static","origin":{"x":1216.0,"y":8928.0,"z":3360.0},"angles":{"x":45.0,"y":135.0,"z":0.0}},{"model":11,"vertLighting":29,"flags":16,"clusters":[1630,1622,1612,1606,1598,442,436,426,418,412],"classname":"prop_static","origin":{"x":-192.0,"y":7872.0,"z":528.0},"angles":{"x":0.0,"y":0.0,"z":0.0}},{"model":4,"vertLighting":30,"flags":16,"clusters":[3862],"classname":"prop_static","origin":{"x":-1248.0,"y":-6736.0,"z":-4066.7},"angles":{"x":0.0,"y":135.0,"z":0.0}},{"model":4,"vertLighting":31,"flags":16,"clusters":[3185],"classname":"prop_static","origin":{"x":1248.0,"y":-6736.0,"z":-4066.7},"angles":{"x":0.0,"y":45.0,"z":0.0}},{"model":12,"vertLighting":32,"flags":16,"clusters":[4089,3267],"classname":"prop_static","origin":{"x":198.0,"y":-10480.0,"z":-5344.0},"angles":{"x":0.0,"y":90.0,"z":0.0}},{"model":4,"vertLighting":33,"flags":16,"clusters":[2370],"classname":"prop_static","origin":{"x":-2591.68,"y":2384.0,"z":-10528.0},"angles":{"x":-90.0,"y":90.0,"z":0.0}},{"model":4,"vertLighting":34,"flags":16,"clusters":[1063],"classname":"prop_static","origin":{"x":2592.32,"y":2384.0,"z":-10528.0},"angles":{"x":-90.0,"y":90.0,"z":0.0}},{"model":4,"vertLighting":35,"flags":16,"clusters":[2103,2032],"classname":"prop_static","origin":{"x":-1024.0,"y":4864.46,"z":-9408.0},"angles":{"x":-90.0,"y":0.0,"z":0.0}},{"model":4,"vertLighting":36,"flags":16,"clusters":[951,898],"classname":"prop_static","origin":{"x":1024.0,"y":4864.46,"z":-9408.0},"angles":{"x":-90.0,"y":180.0,"z":0.0}},{"model":13,"vertLighting":37,"flags":0,"clusters":[4197,4188],"classname":"prop_static","origin":{"x":-1562.04,"y":-14592.0,"z":11219.5},"angles":{"x":0.0,"y":270.0,"z":15.0}},{"model":14,"vertLighting":38,"flags":16,"clusters":[4229,4194],"classname":"prop_static","origin":{"x":-1728.0,"y":-14596.0,"z":10176.0},"angles":{"x":0.0,"y":270.0,"z":-15.0}},{"model":5,"vertLighting":39,"flags":0,"clusters":[4230],"classname":"prop_static","origin":{"x":-2138.03,"y":-14560.0,"z":10608.0},"angles":{"x":0.0,"y":0.0,"z":0.0}},{"model":15,"vertLighting":40,"flags":0,"clusters":[4210,4208,4198,4197,4196],"classname":"prop_static","origin":{"x":-1092.03,"y":-14558.0,"z":10958.0},"angles":{"x":0.0,"y":0.0,"z":0.0}},{"model":6,"vertLighting":41,"flags":0,"clusters":[4195],"classname":"prop_static","origin":{"x":-2138.03,"y":-14176.0,"z":10608.0},"angles":{"x":0.0,"y":0.0,"z":0.0}},{"model":7,"vertLighting":42,"flags":0,"clusters":[4230],"classname":"prop_static","origin":{"x":-2138.03,"y":-14944.0,"z":10608.0},"angles":{"x":0.0,"y":0.0,"z":0.0}},{"model":17,"vertLighting":43,"flags":16,"clusters":[2571,2570,1799,1798,1797,1796,1793,1767],"classname":"prop_static","origin":{"x":-8192.0,"y":7266.0,"z":8067.0},"angles":{"x":0.0,"y":270.0,"z":0.0}}]}